<?xml version="1.0"?>
<Tabela>
	<Configuracoes>
		<HASH>33C5A2733D9F6E70C99BF05876FB5BF4</HASH>
		<NOME>ESO_S1200</NOME>
		<APELIDO>ESOS1200</APELIDO>
		<LEGENDA>ESO_S1200</LEGENDA>
		<LOCAL>N</LOCAL>
		<TIPO>N</TIPO>
		<GENERICA>N</GENERICA>
		<DESENVOLVIMENTO>N</DESENVOLVIMENTO>
		<SOLEITURA>N</SOLEITURA>
		<PROTEGERREGISTRO>N</PROTEGERREGISTRO>
		<POREMPRESA>N</POREMPRESA>
		<PORPERIODO>N</PORPERIODO>
		<PORFILIAL>N</PORFILIAL>
		<AGENDA>N</AGENDA>
		<CODIGOINTERNO>0</CODIGOINTERNO>
		<CLIDEF>N</CLIDEF>
		<FLAGS>0</FLAGS>
		<CHAVEDB2EEE/>
		<TOPICOAJUDA/>
		<TSPACE/>
		<TSPACELONG/>
		<TSPACEINDEX/>
		<Z_GRUPO/>
		<OBSERVACOES/>
		<TABELAFISICA/>
		<TIPOPARTICIONAMENTO>1</TIPOPARTICIONAMENTO>
		<ORIGEM>1</ORIGEM>
		<COMANDO/>
		<Z_EXCLUIDO/>
		<ENTIDADE>EsoS1200</ENTIDADE>
	</Configuracoes>
	<Campos>
		<CODCBO>
			<TABELA>ESO_S1200</TABELA>
			<NOME>CODCBO</NOME>
			<LEGENDAFORMULARIO>CBO</LEGENDAFORMULARIO>
			<LEGENDAGRADE>CBO</LEGENDAGRADE>
			<ORDEM>260</ORDEM>
			<DICA>Classificação Brasileira de Ocupação - CBO</DICA>
			<PAGINA/>
			<CODIGOINTERNO/>
			<SISTEMA>N</SISTEMA>
			<OPCIONAL>S</OPCIONAL>
			<INVISIVEL>N</INVISIVEL>
			<SOLEITURA>N</SOLEITURA>
			<NOVALINHA>N</NOVALINHA>
			<MOSTRARGRID>S</MOSTRARGRID>
			<ALCLIENTE>N</ALCLIENTE>
			<CLASSE>0</CLASSE>
			<HERDARPERMISSAO/>
			<LARGURA>6</LARGURA>
			<MASCARA/>
			<DECIMAIS/>
			<LARGURAFORMULARIO>10</LARGURAFORMULARIO>
			<MAIUSCULAS>N</MAIUSCULAS>
			<ASSUMIR/>
			<ASSUMIRINTEIRO/>
			<ASSUMIRREAL/>
			<ASSUMIRLOGICO>N</ASSUMIRLOGICO>
			<ASSUMIRDATA/>
			<MINIMO/>
			<MAXIMO/>
			<CAMPOMESTRE/>
			<CAMPOMESTREORIGINAL/>
			<ANCESTRAL/>
			<PESQUISAR/>
			<RESULTADO/>
			<TEXTO/>
			<FLAGS>0</FLAGS>
			<FLAGS1>24584</FLAGS1>
			<FLAGS2>0</FLAGS2>
			<CLIDEF>N</CLIDEF>
			<Z_GRUPO/>
			<OBSERVACOES/>
			<PROPRIEDADE>Cbo</PROPRIEDADE>
			<HASH>24B4E970F8389C0F395518712FC167CC</HASH>
		</CODCBO>
		<CPFTRAB>
			<TABELA>ESO_S1200</TABELA>
			<NOME>CPFTRAB</NOME>
			<LEGENDAFORMULARIO>CPF do trabalhador</LEGENDAFORMULARIO>
			<LEGENDAGRADE>CPF do trabalhador</LEGENDAGRADE>
			<ORDEM>180</ORDEM>
			<DICA/>
			<PAGINA/>
			<CODIGOINTERNO/>
			<SISTEMA>N</SISTEMA>
			<OPCIONAL>S</OPCIONAL>
			<INVISIVEL>N</INVISIVEL>
			<SOLEITURA>N</SOLEITURA>
			<NOVALINHA>N</NOVALINHA>
			<MOSTRARGRID>S</MOSTRARGRID>
			<ALCLIENTE>N</ALCLIENTE>
			<CLASSE>0</CLASSE>
			<HERDARPERMISSAO/>
			<LARGURA>11</LARGURA>
			<MASCARA/>
			<DECIMAIS/>
			<LARGURAFORMULARIO>15</LARGURAFORMULARIO>
			<MAIUSCULAS>N</MAIUSCULAS>
			<ASSUMIR/>
			<ASSUMIRINTEIRO/>
			<ASSUMIRREAL/>
			<ASSUMIRLOGICO>N</ASSUMIRLOGICO>
			<ASSUMIRDATA/>
			<MINIMO/>
			<MAXIMO/>
			<CAMPOMESTRE/>
			<CAMPOMESTREORIGINAL/>
			<ANCESTRAL/>
			<PESQUISAR/>
			<RESULTADO/>
			<TEXTO/>
			<FLAGS>0</FLAGS>
			<FLAGS1>24584</FLAGS1>
			<FLAGS2>0</FLAGS2>
			<CLIDEF>N</CLIDEF>
			<Z_GRUPO/>
			<OBSERVACOES/>
			<PROPRIEDADE>CpfDoTrabalhador</PROPRIEDADE>
			<HASH>7E20DCB9B6C313FCA9AC29A4B61EBA4C</HASH>
		</CPFTRAB>
		<DTNASCTO>
			<TABELA>ESO_S1200</TABELA>
			<NOME>DTNASCTO</NOME>
			<LEGENDAFORMULARIO>Data de nascimento</LEGENDAFORMULARIO>
			<LEGENDAGRADE>Data de nascimento</LEGENDAGRADE>
			<ORDEM>250</ORDEM>
			<DICA>Data de nascimento do trabalhador no formato AAAA-MM-DD</DICA>
			<PAGINA/>
			<CODIGOINTERNO/>
			<SISTEMA>N</SISTEMA>
			<OPCIONAL>S</OPCIONAL>
			<INVISIVEL>N</INVISIVEL>
			<SOLEITURA>N</SOLEITURA>
			<NOVALINHA>N</NOVALINHA>
			<MOSTRARGRID>S</MOSTRARGRID>
			<ALCLIENTE>N</ALCLIENTE>
			<CLASSE>0</CLASSE>
			<HERDARPERMISSAO/>
			<LARGURA>10</LARGURA>
			<MASCARA/>
			<DECIMAIS/>
			<LARGURAFORMULARIO>15</LARGURAFORMULARIO>
			<MAIUSCULAS>N</MAIUSCULAS>
			<ASSUMIR/>
			<ASSUMIRINTEIRO/>
			<ASSUMIRREAL/>
			<ASSUMIRLOGICO>N</ASSUMIRLOGICO>
			<ASSUMIRDATA/>
			<MINIMO/>
			<MAXIMO/>
			<CAMPOMESTRE/>
			<CAMPOMESTREORIGINAL/>
			<ANCESTRAL/>
			<PESQUISAR/>
			<RESULTADO/>
			<TEXTO/>
			<FLAGS>0</FLAGS>
			<FLAGS1>24584</FLAGS1>
			<FLAGS2>0</FLAGS2>
			<CLIDEF>N</CLIDEF>
			<Z_GRUPO/>
			<OBSERVACOES/>
			<PROPRIEDADE>DataNascimento</PROPRIEDADE>
			<HASH>94A7C70A39D0BC302DA6660D5E8D8BD3</HASH>
		</DTNASCTO>
		<EVENTO>
			<TABELA>ESO_S1200</TABELA>
			<NOME>EVENTO</NOME>
			<LEGENDAFORMULARIO>Evento</LEGENDAFORMULARIO>
			<LEGENDAGRADE>Evento</LEGENDAGRADE>
			<ORDEM>040</ORDEM>
			<DICA/>
			<PAGINA/>
			<CODIGOINTERNO/>
			<SISTEMA>N</SISTEMA>
			<OPCIONAL>N</OPCIONAL>
			<INVISIVEL>N</INVISIVEL>
			<SOLEITURA>N</SOLEITURA>
			<NOVALINHA>N</NOVALINHA>
			<MOSTRARGRID>S</MOSTRARGRID>
			<ALCLIENTE>N</ALCLIENTE>
			<CLASSE>6</CLASSE>
			<HERDARPERMISSAO/>
			<LARGURA/>
			<MASCARA/>
			<DECIMAIS/>
			<LARGURAFORMULARIO/>
			<MAIUSCULAS>N</MAIUSCULAS>
			<ASSUMIR/>
			<ASSUMIRINTEIRO/>
			<ASSUMIRREAL/>
			<ASSUMIRLOGICO>N</ASSUMIRLOGICO>
			<ASSUMIRDATA/>
			<MINIMO/>
			<MAXIMO/>
			<CAMPOMESTRE/>
			<CAMPOMESTREORIGINAL/>
			<ANCESTRAL/>
			<PESQUISAR>ESO_EVENTO</PESQUISAR>
			<RESULTADO>ESO_EVENTO|PRESTADORESOCIAL</RESULTADO>
			<TEXTO/>
			<FLAGS>4096</FLAGS>
			<FLAGS1>8</FLAGS1>
			<FLAGS2>0</FLAGS2>
			<CLIDEF>N</CLIDEF>
			<Z_GRUPO/>
			<OBSERVACOES/>
			<PROPRIEDADE>Evento</PROPRIEDADE>
			<HASH>90228B235CD9121D311090F92ED3B8AF</HASH>
		</EVENTO>
		<ID>
			<TABELA>ESO_S1200</TABELA>
			<NOME>ID</NOME>
			<LEGENDAFORMULARIO>Identificação única do evento</LEGENDAFORMULARIO>
			<LEGENDAGRADE>Identificação única do evento</LEGENDAGRADE>
			<ORDEM>050</ORDEM>
			<DICA/>
			<PAGINA/>
			<CODIGOINTERNO/>
			<SISTEMA>N</SISTEMA>
			<OPCIONAL>S</OPCIONAL>
			<INVISIVEL>N</INVISIVEL>
			<SOLEITURA>N</SOLEITURA>
			<NOVALINHA>N</NOVALINHA>
			<MOSTRARGRID>S</MOSTRARGRID>
			<ALCLIENTE>N</ALCLIENTE>
			<CLASSE>0</CLASSE>
			<HERDARPERMISSAO/>
			<LARGURA>36</LARGURA>
			<MASCARA/>
			<DECIMAIS/>
			<LARGURAFORMULARIO>50</LARGURAFORMULARIO>
			<MAIUSCULAS>N</MAIUSCULAS>
			<ASSUMIR/>
			<ASSUMIRINTEIRO/>
			<ASSUMIRREAL/>
			<ASSUMIRLOGICO>N</ASSUMIRLOGICO>
			<ASSUMIRDATA/>
			<MINIMO/>
			<MAXIMO/>
			<CAMPOMESTRE/>
			<CAMPOMESTREORIGINAL/>
			<ANCESTRAL/>
			<PESQUISAR/>
			<RESULTADO/>
			<TEXTO/>
			<FLAGS>0</FLAGS>
			<FLAGS1>24584</FLAGS1>
			<FLAGS2>0</FLAGS2>
			<CLIDEF>N</CLIDEF>
			<Z_GRUPO/>
			<OBSERVACOES/>
			<PROPRIEDADE>Id</PROPRIEDADE>
			<HASH>187966880EFC09729142953054BF99FD</HASH>
		</ID>
		<IDEEMPREGADOR>
			<TABELA>ESO_S1200</TABELA>
			<NOME>IDEEMPREGADOR</NOME>
			<LEGENDAFORMULARIO>Informações identificação do empregador</LEGENDAFORMULARIO>
			<LEGENDAGRADE>Informações identificação do empregador</LEGENDAGRADE>
			<ORDEM>140</ORDEM>
			<DICA/>
			<PAGINA/>
			<CODIGOINTERNO/>
			<SISTEMA>N</SISTEMA>
			<OPCIONAL>S</OPCIONAL>
			<INVISIVEL>N</INVISIVEL>
			<SOLEITURA>N</SOLEITURA>
			<NOVALINHA>N</NOVALINHA>
			<MOSTRARGRID>S</MOSTRARGRID>
			<ALCLIENTE>N</ALCLIENTE>
			<CLASSE>15</CLASSE>
			<HERDARPERMISSAO/>
			<LARGURA/>
			<MASCARA/>
			<DECIMAIS/>
			<LARGURAFORMULARIO/>
			<MAIUSCULAS>N</MAIUSCULAS>
			<ASSUMIR/>
			<ASSUMIRINTEIRO/>
			<ASSUMIRREAL/>
			<ASSUMIRLOGICO>N</ASSUMIRLOGICO>
			<ASSUMIRDATA/>
			<MINIMO/>
			<MAXIMO/>
			<CAMPOMESTRE/>
			<CAMPOMESTREORIGINAL/>
			<ANCESTRAL/>
			<PESQUISAR/>
			<RESULTADO/>
			<TEXTO>1#NRINSC|S|TPINSC|S|</TEXTO>
			<FLAGS>0</FLAGS>
			<FLAGS1>8</FLAGS1>
			<FLAGS2>0</FLAGS2>
			<CLIDEF>N</CLIDEF>
			<Z_GRUPO/>
			<OBSERVACOES/>
			<PROPRIEDADE>InformacoesIdentificacaoDoEmpregador</PROPRIEDADE>
			<HASH>B5FFC274B541B81CD69A4F37EE9B71BA</HASH>
		</IDEEMPREGADOR>
		<IDEEVENTO>
			<TABELA>ESO_S1200</TABELA>
			<NOME>IDEEVENTO</NOME>
			<LEGENDAFORMULARIO>Informações de identificação do evento</LEGENDAFORMULARIO>
			<LEGENDAGRADE>Informações de identificação do evento</LEGENDAGRADE>
			<ORDEM>060</ORDEM>
			<DICA/>
			<PAGINA/>
			<CODIGOINTERNO/>
			<SISTEMA>N</SISTEMA>
			<OPCIONAL>S</OPCIONAL>
			<INVISIVEL>N</INVISIVEL>
			<SOLEITURA>N</SOLEITURA>
			<NOVALINHA>N</NOVALINHA>
			<MOSTRARGRID>S</MOSTRARGRID>
			<ALCLIENTE>N</ALCLIENTE>
			<CLASSE>15</CLASSE>
			<HERDARPERMISSAO/>
			<LARGURA/>
			<MASCARA/>
			<DECIMAIS/>
			<LARGURAFORMULARIO/>
			<MAIUSCULAS>N</MAIUSCULAS>
			<ASSUMIR/>
			<ASSUMIRINTEIRO/>
			<ASSUMIRREAL/>
			<ASSUMIRLOGICO>N</ASSUMIRLOGICO>
			<ASSUMIRDATA/>
			<MINIMO/>
			<MAXIMO/>
			<CAMPOMESTRE/>
			<CAMPOMESTREORIGINAL/>
			<ANCESTRAL/>
			<PESQUISAR/>
			<RESULTADO/>
			<TEXTO>1#INDAPURACAO|S|INDRETIF|S|NRRECIBO|S|PERAPUR|S|PROCEMI|S|TPAMB|S|VERPROC|S|</TEXTO>
			<FLAGS>0</FLAGS>
			<FLAGS1>8</FLAGS1>
			<FLAGS2>0</FLAGS2>
			<CLIDEF>N</CLIDEF>
			<Z_GRUPO/>
			<OBSERVACOES/>
			<PROPRIEDADE>InformacoesIdentificacaoDoEvento</PROPRIEDADE>
			<HASH>A4C2E98D4B15029FD0319D974DEB4E5C</HASH>
		</IDEEVENTO>
		<IDETRABALHADOR>
			<TABELA>ESO_S1200</TABELA>
			<NOME>IDETRABALHADOR</NOME>
			<LEGENDAFORMULARIO>Identificação básica do trabalhador</LEGENDAFORMULARIO>
			<LEGENDAGRADE>Identificação básica do trabalhador</LEGENDAGRADE>
			<ORDEM>170</ORDEM>
			<DICA>Apresenta a identificação básica do trabalhador ao qual se refere o  evento de remuneração.</DICA>
			<PAGINA/>
			<CODIGOINTERNO/>
			<SISTEMA>N</SISTEMA>
			<OPCIONAL>S</OPCIONAL>
			<INVISIVEL>N</INVISIVEL>
			<SOLEITURA>N</SOLEITURA>
			<NOVALINHA>N</NOVALINHA>
			<MOSTRARGRID>S</MOSTRARGRID>
			<ALCLIENTE>N</ALCLIENTE>
			<CLASSE>15</CLASSE>
			<HERDARPERMISSAO/>
			<LARGURA/>
			<MASCARA/>
			<DECIMAIS/>
			<LARGURAFORMULARIO/>
			<MAIUSCULAS>N</MAIUSCULAS>
			<ASSUMIR/>
			<ASSUMIRINTEIRO/>
			<ASSUMIRREAL/>
			<ASSUMIRLOGICO>N</ASSUMIRLOGICO>
			<ASSUMIRDATA/>
			<MINIMO/>
			<MAXIMO/>
			<CAMPOMESTRE/>
			<CAMPOMESTREORIGINAL/>
			<ANCESTRAL/>
			<PESQUISAR/>
			<RESULTADO/>
			<TEXTO>1#CPFTRAB|S|NISTRAB|S|INFOMV|S|INFOCOMPLEM|S|</TEXTO>
			<FLAGS>0</FLAGS>
			<FLAGS1>8</FLAGS1>
			<FLAGS2>0</FLAGS2>
			<CLIDEF>N</CLIDEF>
			<Z_GRUPO/>
			<OBSERVACOES/>
			<PROPRIEDADE>IdentificacaoBasicaDoTrabalhador</PROPRIEDADE>
			<HASH>A5845D2C98CC4F3E8EC820FBC736F3F3</HASH>
		</IDETRABALHADOR>
		<INDAPURACAO>
			<TABELA>ESO_S1200</TABELA>
			<NOME>INDAPURACAO</NOME>
			<LEGENDAFORMULARIO>Indicativo de período de apuração</LEGENDAFORMULARIO>
			<LEGENDAGRADE>Indicativo de período de apuração</LEGENDAGRADE>
			<ORDEM>090</ORDEM>
			<DICA>1 - Mensal | 2 - Anual (13° salário)</DICA>
			<PAGINA/>
			<CODIGOINTERNO/>
			<SISTEMA>N</SISTEMA>
			<OPCIONAL>S</OPCIONAL>
			<INVISIVEL>N</INVISIVEL>
			<SOLEITURA>N</SOLEITURA>
			<NOVALINHA>N</NOVALINHA>
			<MOSTRARGRID>S</MOSTRARGRID>
			<ALCLIENTE>N</ALCLIENTE>
			<CLASSE>0</CLASSE>
			<HERDARPERMISSAO/>
			<LARGURA>2</LARGURA>
			<MASCARA/>
			<DECIMAIS/>
			<LARGURAFORMULARIO>5</LARGURAFORMULARIO>
			<MAIUSCULAS>N</MAIUSCULAS>
			<ASSUMIR/>
			<ASSUMIRINTEIRO/>
			<ASSUMIRREAL/>
			<ASSUMIRLOGICO>N</ASSUMIRLOGICO>
			<ASSUMIRDATA/>
			<MINIMO/>
			<MAXIMO/>
			<CAMPOMESTRE/>
			<CAMPOMESTREORIGINAL/>
			<ANCESTRAL/>
			<PESQUISAR/>
			<RESULTADO/>
			<TEXTO/>
			<FLAGS>0</FLAGS>
			<FLAGS1>24584</FLAGS1>
			<FLAGS2>0</FLAGS2>
			<CLIDEF>N</CLIDEF>
			<Z_GRUPO/>
			<OBSERVACOES/>
			<PROPRIEDADE>IndicativoPeriodoApuracao</PROPRIEDADE>
			<HASH>0C64E5974EB88DB18836181C595472D0</HASH>
		</INDAPURACAO>
		<INDMV>
			<TABELA>ESO_S1200</TABELA>
			<NOME>INDMV</NOME>
			<LEGENDAFORMULARIO>Indicador de múltiplo vínculo</LEGENDAFORMULARIO>
			<LEGENDAGRADE>Indicador de múltiplo vínculo</LEGENDAGRADE>
			<ORDEM>210</ORDEM>
			<DICA/>
			<PAGINA/>
			<CODIGOINTERNO/>
			<SISTEMA>N</SISTEMA>
			<OPCIONAL>S</OPCIONAL>
			<INVISIVEL>N</INVISIVEL>
			<SOLEITURA>N</SOLEITURA>
			<NOVALINHA>N</NOVALINHA>
			<MOSTRARGRID>S</MOSTRARGRID>
			<ALCLIENTE>N</ALCLIENTE>
			<CLASSE>0</CLASSE>
			<HERDARPERMISSAO/>
			<LARGURA>2</LARGURA>
			<MASCARA/>
			<DECIMAIS/>
			<LARGURAFORMULARIO>5</LARGURAFORMULARIO>
			<MAIUSCULAS>N</MAIUSCULAS>
			<ASSUMIR/>
			<ASSUMIRINTEIRO/>
			<ASSUMIRREAL/>
			<ASSUMIRLOGICO>N</ASSUMIRLOGICO>
			<ASSUMIRDATA/>
			<MINIMO/>
			<MAXIMO/>
			<CAMPOMESTRE/>
			<CAMPOMESTREORIGINAL/>
			<ANCESTRAL/>
			<PESQUISAR/>
			<RESULTADO/>
			<TEXTO/>
			<FLAGS>0</FLAGS>
			<FLAGS1>24584</FLAGS1>
			<FLAGS2>0</FLAGS2>
			<CLIDEF>N</CLIDEF>
			<Z_GRUPO/>
			<OBSERVACOES/>
			<PROPRIEDADE>IndicadorMultiploVinculo</PROPRIEDADE>
			<HASH>61504F765482100CB8994C08B0991761</HASH>
		</INDMV>
		<INDRETIF>
			<TABELA>ESO_S1200</TABELA>
			<NOME>INDRETIF</NOME>
			<LEGENDAFORMULARIO>Original/Retificação</LEGENDAFORMULARIO>
			<LEGENDAGRADE>Original/Retificação</LEGENDAGRADE>
			<ORDEM>070</ORDEM>
			<DICA/>
			<PAGINA/>
			<CODIGOINTERNO/>
			<SISTEMA>N</SISTEMA>
			<OPCIONAL>S</OPCIONAL>
			<INVISIVEL>N</INVISIVEL>
			<SOLEITURA>N</SOLEITURA>
			<NOVALINHA>S</NOVALINHA>
			<MOSTRARGRID>S</MOSTRARGRID>
			<ALCLIENTE>N</ALCLIENTE>
			<CLASSE>0</CLASSE>
			<HERDARPERMISSAO/>
			<LARGURA>2</LARGURA>
			<MASCARA/>
			<DECIMAIS/>
			<LARGURAFORMULARIO>5</LARGURAFORMULARIO>
			<MAIUSCULAS>N</MAIUSCULAS>
			<ASSUMIR/>
			<ASSUMIRINTEIRO/>
			<ASSUMIRREAL/>
			<ASSUMIRLOGICO>N</ASSUMIRLOGICO>
			<ASSUMIRDATA/>
			<MINIMO/>
			<MAXIMO/>
			<CAMPOMESTRE/>
			<CAMPOMESTREORIGINAL/>
			<ANCESTRAL/>
			<PESQUISAR/>
			<RESULTADO/>
			<TEXTO/>
			<FLAGS>0</FLAGS>
			<FLAGS1>24584</FLAGS1>
			<FLAGS2>0</FLAGS2>
			<CLIDEF>N</CLIDEF>
			<Z_GRUPO/>
			<OBSERVACOES/>
			<PROPRIEDADE>OriginalRetificacao</PROPRIEDADE>
			<HASH>B47F65255A1C7161E1629EF6E4737449</HASH>
		</INDRETIF>
		<INFOCOMPLEM>
			<TABELA>ESO_S1200</TABELA>
			<NOME>INFOCOMPLEM</NOME>
			<LEGENDAFORMULARIO>Informações complementares</LEGENDAFORMULARIO>
			<LEGENDAGRADE>Informações complementares</LEGENDAGRADE>
			<ORDEM>230</ORDEM>
			<DICA/>
			<PAGINA/>
			<CODIGOINTERNO/>
			<SISTEMA>N</SISTEMA>
			<OPCIONAL>S</OPCIONAL>
			<INVISIVEL>N</INVISIVEL>
			<SOLEITURA>N</SOLEITURA>
			<NOVALINHA>N</NOVALINHA>
			<MOSTRARGRID>S</MOSTRARGRID>
			<ALCLIENTE>N</ALCLIENTE>
			<CLASSE>15</CLASSE>
			<HERDARPERMISSAO/>
			<LARGURA/>
			<MASCARA/>
			<DECIMAIS/>
			<LARGURAFORMULARIO/>
			<MAIUSCULAS>N</MAIUSCULAS>
			<ASSUMIR/>
			<ASSUMIRINTEIRO/>
			<ASSUMIRREAL/>
			<ASSUMIRLOGICO>N</ASSUMIRLOGICO>
			<ASSUMIRDATA/>
			<MINIMO/>
			<MAXIMO/>
			<CAMPOMESTRE/>
			<CAMPOMESTREORIGINAL/>
			<ANCESTRAL/>
			<PESQUISAR/>
			<RESULTADO/>
			<TEXTO>1#NMTRAB|S|DTNASCTO|S|CODCBO|S|</TEXTO>
			<FLAGS>0</FLAGS>
			<FLAGS1>8</FLAGS1>
			<FLAGS2>0</FLAGS2>
			<CLIDEF>N</CLIDEF>
			<Z_GRUPO/>
			<OBSERVACOES/>
			<PROPRIEDADE>InformacoesComplementares</PROPRIEDADE>
			<HASH>52AC6630CCF866B3A93C059887468931</HASH>
		</INFOCOMPLEM>
		<INFOMV>
			<TABELA>ESO_S1200</TABELA>
			<NOME>INFOMV</NOME>
			<LEGENDAFORMULARIO>Informações de múltiplo vínculo</LEGENDAFORMULARIO>
			<LEGENDAGRADE>Informações de múltiplo vínculo</LEGENDAGRADE>
			<ORDEM>200</ORDEM>
			<DICA/>
			<PAGINA/>
			<CODIGOINTERNO/>
			<SISTEMA>N</SISTEMA>
			<OPCIONAL>S</OPCIONAL>
			<INVISIVEL>N</INVISIVEL>
			<SOLEITURA>N</SOLEITURA>
			<NOVALINHA>N</NOVALINHA>
			<MOSTRARGRID>S</MOSTRARGRID>
			<ALCLIENTE>N</ALCLIENTE>
			<CLASSE>15</CLASSE>
			<HERDARPERMISSAO/>
			<LARGURA/>
			<MASCARA/>
			<DECIMAIS/>
			<LARGURAFORMULARIO/>
			<MAIUSCULAS>N</MAIUSCULAS>
			<ASSUMIR/>
			<ASSUMIRINTEIRO/>
			<ASSUMIRREAL/>
			<ASSUMIRLOGICO>N</ASSUMIRLOGICO>
			<ASSUMIRDATA/>
			<MINIMO/>
			<MAXIMO/>
			<CAMPOMESTRE/>
			<CAMPOMESTREORIGINAL/>
			<ANCESTRAL/>
			<PESQUISAR/>
			<RESULTADO/>
			<TEXTO>1#INDMV|S|</TEXTO>
			<FLAGS>0</FLAGS>
			<FLAGS1>8</FLAGS1>
			<FLAGS2>0</FLAGS2>
			<CLIDEF>N</CLIDEF>
			<Z_GRUPO/>
			<OBSERVACOES/>
			<PROPRIEDADE>InformacoesMultiploVinculo</PROPRIEDADE>
			<HASH>D47F53794D570B4EF5B930300A2C42DA</HASH>
		</INFOMV>
		<NISTRAB>
			<TABELA>ESO_S1200</TABELA>
			<NOME>NISTRAB</NOME>
			<LEGENDAFORMULARIO>Número de Identificação Social - NIS</LEGENDAFORMULARIO>
			<LEGENDAGRADE>Número de Identificação Social - NIS</LEGENDAGRADE>
			<ORDEM>190</ORDEM>
			<DICA>PIS, PASEP ou NIT</DICA>
			<PAGINA/>
			<CODIGOINTERNO/>
			<SISTEMA>N</SISTEMA>
			<OPCIONAL>S</OPCIONAL>
			<INVISIVEL>N</INVISIVEL>
			<SOLEITURA>N</SOLEITURA>
			<NOVALINHA>N</NOVALINHA>
			<MOSTRARGRID>S</MOSTRARGRID>
			<ALCLIENTE>N</ALCLIENTE>
			<CLASSE>0</CLASSE>
			<HERDARPERMISSAO/>
			<LARGURA>11</LARGURA>
			<MASCARA/>
			<DECIMAIS/>
			<LARGURAFORMULARIO>15</LARGURAFORMULARIO>
			<MAIUSCULAS>N</MAIUSCULAS>
			<ASSUMIR/>
			<ASSUMIRINTEIRO/>
			<ASSUMIRREAL/>
			<ASSUMIRLOGICO>N</ASSUMIRLOGICO>
			<ASSUMIRDATA/>
			<MINIMO/>
			<MAXIMO/>
			<CAMPOMESTRE/>
			<CAMPOMESTREORIGINAL/>
			<ANCESTRAL/>
			<PESQUISAR/>
			<RESULTADO/>
			<TEXTO/>
			<FLAGS>0</FLAGS>
			<FLAGS1>24584</FLAGS1>
			<FLAGS2>0</FLAGS2>
			<CLIDEF>N</CLIDEF>
			<Z_GRUPO/>
			<OBSERVACOES/>
			<PROPRIEDADE>NumeroIdentificacaoSocialNis</PROPRIEDADE>
			<HASH>6AA6FB5CD644A5045974FF02C9484471</HASH>
		</NISTRAB>
		<NMTRAB>
			<TABELA>ESO_S1200</TABELA>
			<NOME>NMTRAB</NOME>
			<LEGENDAFORMULARIO>Nome do Trabalhador</LEGENDAFORMULARIO>
			<LEGENDAGRADE>Nome do Trabalhador</LEGENDAGRADE>
			<ORDEM>240</ORDEM>
			<DICA/>
			<PAGINA/>
			<CODIGOINTERNO/>
			<SISTEMA>N</SISTEMA>
			<OPCIONAL>S</OPCIONAL>
			<INVISIVEL>N</INVISIVEL>
			<SOLEITURA>N</SOLEITURA>
			<NOVALINHA>N</NOVALINHA>
			<MOSTRARGRID>S</MOSTRARGRID>
			<ALCLIENTE>N</ALCLIENTE>
			<CLASSE>0</CLASSE>
			<HERDARPERMISSAO/>
			<LARGURA>70</LARGURA>
			<MASCARA/>
			<DECIMAIS/>
			<LARGURAFORMULARIO>70</LARGURAFORMULARIO>
			<MAIUSCULAS>N</MAIUSCULAS>
			<ASSUMIR/>
			<ASSUMIRINTEIRO/>
			<ASSUMIRREAL/>
			<ASSUMIRLOGICO>N</ASSUMIRLOGICO>
			<ASSUMIRDATA/>
			<MINIMO/>
			<MAXIMO/>
			<CAMPOMESTRE/>
			<CAMPOMESTREORIGINAL/>
			<ANCESTRAL/>
			<PESQUISAR/>
			<RESULTADO/>
			<TEXTO/>
			<FLAGS>0</FLAGS>
			<FLAGS1>24584</FLAGS1>
			<FLAGS2>0</FLAGS2>
			<CLIDEF>N</CLIDEF>
			<Z_GRUPO/>
			<OBSERVACOES/>
			<PROPRIEDADE>NomeDoTrabalhador</PROPRIEDADE>
			<HASH>BB7EE1794C1004B7B499B77B872E48DA</HASH>
		</NMTRAB>
		<NRINSC>
			<TABELA>ESO_S1200</TABELA>
			<NOME>NRINSC</NOME>
			<LEGENDAFORMULARIO>Número de inscrição</LEGENDAFORMULARIO>
			<LEGENDAGRADE>Número de inscrição</LEGENDAGRADE>
			<ORDEM>160</ORDEM>
			<DICA/>
			<PAGINA/>
			<CODIGOINTERNO/>
			<SISTEMA>N</SISTEMA>
			<OPCIONAL>S</OPCIONAL>
			<INVISIVEL>N</INVISIVEL>
			<SOLEITURA>N</SOLEITURA>
			<NOVALINHA>N</NOVALINHA>
			<MOSTRARGRID>S</MOSTRARGRID>
			<ALCLIENTE>N</ALCLIENTE>
			<CLASSE>0</CLASSE>
			<HERDARPERMISSAO/>
			<LARGURA>15</LARGURA>
			<MASCARA/>
			<DECIMAIS/>
			<LARGURAFORMULARIO>20</LARGURAFORMULARIO>
			<MAIUSCULAS>N</MAIUSCULAS>
			<ASSUMIR/>
			<ASSUMIRINTEIRO/>
			<ASSUMIRREAL/>
			<ASSUMIRLOGICO>N</ASSUMIRLOGICO>
			<ASSUMIRDATA/>
			<MINIMO/>
			<MAXIMO/>
			<CAMPOMESTRE/>
			<CAMPOMESTREORIGINAL/>
			<ANCESTRAL/>
			<PESQUISAR/>
			<RESULTADO/>
			<TEXTO/>
			<FLAGS>0</FLAGS>
			<FLAGS1>24584</FLAGS1>
			<FLAGS2>0</FLAGS2>
			<CLIDEF>N</CLIDEF>
			<Z_GRUPO/>
			<OBSERVACOES/>
			<PROPRIEDADE>NumeroInscricao</PROPRIEDADE>
			<HASH>91CE236C81A3D01268F9F3B36AA33432</HASH>
		</NRINSC>
		<NRRECIBO>
			<TABELA>ESO_S1200</TABELA>
			<NOME>NRRECIBO</NOME>
			<LEGENDAFORMULARIO>Número do recibo</LEGENDAFORMULARIO>
			<LEGENDAGRADE>Número do recibo</LEGENDAGRADE>
			<ORDEM>080</ORDEM>
			<DICA/>
			<PAGINA/>
			<CODIGOINTERNO/>
			<SISTEMA>N</SISTEMA>
			<OPCIONAL>S</OPCIONAL>
			<INVISIVEL>N</INVISIVEL>
			<SOLEITURA>N</SOLEITURA>
			<NOVALINHA>N</NOVALINHA>
			<MOSTRARGRID>S</MOSTRARGRID>
			<ALCLIENTE>N</ALCLIENTE>
			<CLASSE>0</CLASSE>
			<HERDARPERMISSAO/>
			<LARGURA>40</LARGURA>
			<MASCARA/>
			<DECIMAIS/>
			<LARGURAFORMULARIO>50</LARGURAFORMULARIO>
			<MAIUSCULAS>N</MAIUSCULAS>
			<ASSUMIR/>
			<ASSUMIRINTEIRO/>
			<ASSUMIRREAL/>
			<ASSUMIRLOGICO>N</ASSUMIRLOGICO>
			<ASSUMIRDATA/>
			<MINIMO/>
			<MAXIMO/>
			<CAMPOMESTRE/>
			<CAMPOMESTREORIGINAL/>
			<ANCESTRAL/>
			<PESQUISAR/>
			<RESULTADO/>
			<TEXTO/>
			<FLAGS>0</FLAGS>
			<FLAGS1>24584</FLAGS1>
			<FLAGS2>0</FLAGS2>
			<CLIDEF>N</CLIDEF>
			<Z_GRUPO/>
			<OBSERVACOES/>
			<PROPRIEDADE>NumeroDoRecibo</PROPRIEDADE>
			<HASH>7F6A978417C16F3DCBA525F051D88F2E</HASH>
		</NRRECIBO>
		<PERAPUR>
			<TABELA>ESO_S1200</TABELA>
			<NOME>PERAPUR</NOME>
			<LEGENDAFORMULARIO>Período de apuração</LEGENDAFORMULARIO>
			<LEGENDAGRADE>Período de apuração</LEGENDAGRADE>
			<ORDEM>100</ORDEM>
			<DICA/>
			<PAGINA/>
			<CODIGOINTERNO/>
			<SISTEMA>N</SISTEMA>
			<OPCIONAL>S</OPCIONAL>
			<INVISIVEL>N</INVISIVEL>
			<SOLEITURA>N</SOLEITURA>
			<NOVALINHA>N</NOVALINHA>
			<MOSTRARGRID>S</MOSTRARGRID>
			<ALCLIENTE>N</ALCLIENTE>
			<CLASSE>0</CLASSE>
			<HERDARPERMISSAO/>
			<LARGURA>7</LARGURA>
			<MASCARA/>
			<DECIMAIS/>
			<LARGURAFORMULARIO>15</LARGURAFORMULARIO>
			<MAIUSCULAS>N</MAIUSCULAS>
			<ASSUMIR/>
			<ASSUMIRINTEIRO/>
			<ASSUMIRREAL/>
			<ASSUMIRLOGICO>N</ASSUMIRLOGICO>
			<ASSUMIRDATA/>
			<MINIMO/>
			<MAXIMO/>
			<CAMPOMESTRE/>
			<CAMPOMESTREORIGINAL/>
			<ANCESTRAL/>
			<PESQUISAR/>
			<RESULTADO/>
			<TEXTO/>
			<FLAGS>0</FLAGS>
			<FLAGS1>24584</FLAGS1>
			<FLAGS2>0</FLAGS2>
			<CLIDEF>N</CLIDEF>
			<Z_GRUPO/>
			<OBSERVACOES/>
			<PROPRIEDADE>PeriodoApuracao</PROPRIEDADE>
			<HASH>E7C26976E7C2D1E76C32FC5E75BAFF1E</HASH>
		</PERAPUR>
		<PROCEMI>
			<TABELA>ESO_S1200</TABELA>
			<NOME>PROCEMI</NOME>
			<LEGENDAFORMULARIO>Processo de emissão do evento</LEGENDAFORMULARIO>
			<LEGENDAGRADE>Processo de emissão do evento</LEGENDAGRADE>
			<ORDEM>120</ORDEM>
			<DICA>1- Aplicativo do empregador | 2 - Aplicativo governamental</DICA>
			<PAGINA/>
			<CODIGOINTERNO/>
			<SISTEMA>N</SISTEMA>
			<OPCIONAL>S</OPCIONAL>
			<INVISIVEL>N</INVISIVEL>
			<SOLEITURA>N</SOLEITURA>
			<NOVALINHA>N</NOVALINHA>
			<MOSTRARGRID>S</MOSTRARGRID>
			<ALCLIENTE>N</ALCLIENTE>
			<CLASSE>0</CLASSE>
			<HERDARPERMISSAO/>
			<LARGURA>2</LARGURA>
			<MASCARA/>
			<DECIMAIS/>
			<LARGURAFORMULARIO>5</LARGURAFORMULARIO>
			<MAIUSCULAS>N</MAIUSCULAS>
			<ASSUMIR/>
			<ASSUMIRINTEIRO/>
			<ASSUMIRREAL/>
			<ASSUMIRLOGICO>N</ASSUMIRLOGICO>
			<ASSUMIRDATA/>
			<MINIMO/>
			<MAXIMO/>
			<CAMPOMESTRE/>
			<CAMPOMESTREORIGINAL/>
			<ANCESTRAL/>
			<PESQUISAR/>
			<RESULTADO/>
			<TEXTO/>
			<FLAGS>0</FLAGS>
			<FLAGS1>24584</FLAGS1>
			<FLAGS2>0</FLAGS2>
			<CLIDEF>N</CLIDEF>
			<Z_GRUPO/>
			<OBSERVACOES/>
			<PROPRIEDADE>ProcessoEmissaoDoEvento</PROPRIEDADE>
			<HASH>FD02DD9C7994A3AAEC1CC41044526A21</HASH>
		</PROCEMI>
		<TPAMB>
			<TABELA>ESO_S1200</TABELA>
			<NOME>TPAMB</NOME>
			<LEGENDAFORMULARIO>Identificação do ambiente</LEGENDAFORMULARIO>
			<LEGENDAGRADE>Identificação do ambiente</LEGENDAGRADE>
			<ORDEM>110</ORDEM>
			<DICA>1 - Produção | 2 - Produção restrita - dados reais | 3 - Produção restrita - dados fictícios</DICA>
			<PAGINA/>
			<CODIGOINTERNO/>
			<SISTEMA>N</SISTEMA>
			<OPCIONAL>S</OPCIONAL>
			<INVISIVEL>N</INVISIVEL>
			<SOLEITURA>N</SOLEITURA>
			<NOVALINHA>N</NOVALINHA>
			<MOSTRARGRID>S</MOSTRARGRID>
			<ALCLIENTE>N</ALCLIENTE>
			<CLASSE>0</CLASSE>
			<HERDARPERMISSAO/>
			<LARGURA>2</LARGURA>
			<MASCARA/>
			<DECIMAIS/>
			<LARGURAFORMULARIO>5</LARGURAFORMULARIO>
			<MAIUSCULAS>N</MAIUSCULAS>
			<ASSUMIR/>
			<ASSUMIRINTEIRO/>
			<ASSUMIRREAL/>
			<ASSUMIRLOGICO>N</ASSUMIRLOGICO>
			<ASSUMIRDATA/>
			<MINIMO/>
			<MAXIMO/>
			<CAMPOMESTRE/>
			<CAMPOMESTREORIGINAL/>
			<ANCESTRAL/>
			<PESQUISAR/>
			<RESULTADO/>
			<TEXTO/>
			<FLAGS>0</FLAGS>
			<FLAGS1>24584</FLAGS1>
			<FLAGS2>0</FLAGS2>
			<CLIDEF>N</CLIDEF>
			<Z_GRUPO/>
			<OBSERVACOES/>
			<PROPRIEDADE>IdentificacaoDoAmbiente</PROPRIEDADE>
			<HASH>6418C487EA9AB1B6E29445A7578A9DF2</HASH>
		</TPAMB>
		<TPINSC>
			<TABELA>ESO_S1200</TABELA>
			<NOME>TPINSC</NOME>
			<LEGENDAFORMULARIO>Tipo de inscrição</LEGENDAFORMULARIO>
			<LEGENDAGRADE>Tipo de inscrição</LEGENDAGRADE>
			<ORDEM>150</ORDEM>
			<DICA/>
			<PAGINA/>
			<CODIGOINTERNO/>
			<SISTEMA>N</SISTEMA>
			<OPCIONAL>S</OPCIONAL>
			<INVISIVEL>N</INVISIVEL>
			<SOLEITURA>N</SOLEITURA>
			<NOVALINHA>N</NOVALINHA>
			<MOSTRARGRID>S</MOSTRARGRID>
			<ALCLIENTE>N</ALCLIENTE>
			<CLASSE>0</CLASSE>
			<HERDARPERMISSAO/>
			<LARGURA>2</LARGURA>
			<MASCARA/>
			<DECIMAIS/>
			<LARGURAFORMULARIO>5</LARGURAFORMULARIO>
			<MAIUSCULAS>N</MAIUSCULAS>
			<ASSUMIR/>
			<ASSUMIRINTEIRO/>
			<ASSUMIRREAL/>
			<ASSUMIRLOGICO>N</ASSUMIRLOGICO>
			<ASSUMIRDATA/>
			<MINIMO/>
			<MAXIMO/>
			<CAMPOMESTRE/>
			<CAMPOMESTREORIGINAL/>
			<ANCESTRAL/>
			<PESQUISAR/>
			<RESULTADO/>
			<TEXTO/>
			<FLAGS>0</FLAGS>
			<FLAGS1>24584</FLAGS1>
			<FLAGS2>0</FLAGS2>
			<CLIDEF>N</CLIDEF>
			<Z_GRUPO/>
			<OBSERVACOES/>
			<PROPRIEDADE>TipoInscricao</PROPRIEDADE>
			<HASH>E083B75C4D303188347753974A49A51B</HASH>
		</TPINSC>
		<VERPROC>
			<TABELA>ESO_S1200</TABELA>
			<NOME>VERPROC</NOME>
			<LEGENDAFORMULARIO>Versão do processo de emissão do evento</LEGENDAFORMULARIO>
			<LEGENDAGRADE>Versão do processo de emissão do evento</LEGENDAGRADE>
			<ORDEM>130</ORDEM>
			<DICA>Versão do aplicativo emissor do evento</DICA>
			<PAGINA/>
			<CODIGOINTERNO/>
			<SISTEMA>N</SISTEMA>
			<OPCIONAL>S</OPCIONAL>
			<INVISIVEL>N</INVISIVEL>
			<SOLEITURA>N</SOLEITURA>
			<NOVALINHA>N</NOVALINHA>
			<MOSTRARGRID>S</MOSTRARGRID>
			<ALCLIENTE>N</ALCLIENTE>
			<CLASSE>0</CLASSE>
			<HERDARPERMISSAO/>
			<LARGURA>20</LARGURA>
			<MASCARA/>
			<DECIMAIS/>
			<LARGURAFORMULARIO>25</LARGURAFORMULARIO>
			<MAIUSCULAS>N</MAIUSCULAS>
			<ASSUMIR/>
			<ASSUMIRINTEIRO/>
			<ASSUMIRREAL/>
			<ASSUMIRLOGICO>N</ASSUMIRLOGICO>
			<ASSUMIRDATA/>
			<MINIMO/>
			<MAXIMO/>
			<CAMPOMESTRE/>
			<CAMPOMESTREORIGINAL/>
			<ANCESTRAL/>
			<PESQUISAR/>
			<RESULTADO/>
			<TEXTO/>
			<FLAGS>0</FLAGS>
			<FLAGS1>24584</FLAGS1>
			<FLAGS2>0</FLAGS2>
			<CLIDEF>N</CLIDEF>
			<Z_GRUPO/>
			<OBSERVACOES/>
			<PROPRIEDADE>VersaoDoProcessoEmissaoDoEvento</PROPRIEDADE>
			<HASH>3CF55C82356D264C9B359D8FEF4E9A4C</HASH>
		</VERPROC>
	</Campos>
	<EntidadesEspecializadas>
		<Benner.Saude.Entidades.Financeiro.eSocial.EsoS1200>
			<Z_GRUPO/>
			<ENTIDADE>ESO_S1200</ENTIDADE>
			<TIPO>Benner.Saude.Entidades.Financeiro.eSocial.EsoS1200</TIPO>
			<ARQUIVO>Benner.Saude.Entidades</ARQUIVO>
			<ANCESTRAL/>
			<INTERFACE/>
			<HASH>0907DEF91653C37C8793E400D3A80AA7</HASH>
		</Benner.Saude.Entidades.Financeiro.eSocial.EsoS1200>
	</EntidadesEspecializadas>
</Tabela>
