<?xml version="1.0"?>
<Tabela>
	<Configuracoes>
		<HASH>20C07A8DA9F10F83982DD78B08A4BDAB</HASH>
		<NOME>SAM_COMPETENCIAPARTOS</NOME>
		<APELIDO/>
		<LEGENDA>SAM_COMPETENCIAPARTOS</LEGENDA>
		<LOCAL>N</LOCAL>
		<TIPO>N</TIPO>
		<GENERICA>N</GENERICA>
		<DESENVOLVIMENTO>N</DESENVOLVIMENTO>
		<SOLEITURA>N</SOLEITURA>
		<PROTEGERREGISTRO>N</PROTEGERREGISTRO>
		<POREMPRESA>N</POREMPRESA>
		<PORPERIODO>N</PORPERIODO>
		<PORFILIAL>N</PORFILIAL>
		<AGENDA>N</AGENDA>
		<CODIGOINTERNO>0</CODIGOINTERNO>
		<CLIDEF>N</CLIDEF>
		<FLAGS>0</FLAGS>
		<CHAVEDB2EEE/>
		<TOPICOAJUDA/>
		<TSPACE/>
		<TSPACELONG/>
		<TSPACEINDEX/>
		<Z_GRUPO/>
		<OBSERVACOES>{\rtf1\fbidis\ansi\deff0{\fonttbl{\f0\fswiss\fprq2\fcharset0 Arial;}{\f1\fnil\fcharset0 MS Sans Serif;}}
\viewkind4\uc1\pard\ltrpar\lang1046\b\f0\fs18 SMS 811825\b0\f1\fs16 
\par }</OBSERVACOES>
		<TABELAFISICA/>
		<TIPOPARTICIONAMENTO>1</TIPOPARTICIONAMENTO>
		<ORIGEM>1</ORIGEM>
		<COMANDO/>
		<Z_EXCLUIDO/>
		<ENTIDADE>SamCompetenciapartos</ENTIDADE>
	</Configuracoes>
	<Campos>
		<BOTAOPROCESSAR>
			<TABELA>SAM_COMPETENCIAPARTOS</TABELA>
			<NOME>BOTAOPROCESSAR</NOME>
			<LEGENDAFORMULARIO>Processar com base no SIP</LEGENDAFORMULARIO>
			<LEGENDAGRADE>Processar com base no SIP</LEGENDAGRADE>
			<ORDEM>060</ORDEM>
			<DICA/>
			<PAGINA/>
			<CODIGOINTERNO/>
			<SISTEMA>N</SISTEMA>
			<OPCIONAL>S</OPCIONAL>
			<INVISIVEL>N</INVISIVEL>
			<SOLEITURA>N</SOLEITURA>
			<NOVALINHA>N</NOVALINHA>
			<MOSTRARGRID>S</MOSTRARGRID>
			<ALCLIENTE>N</ALCLIENTE>
			<CLASSE>11</CLASSE>
			<HERDARPERMISSAO/>
			<LARGURA/>
			<MASCARA/>
			<DECIMAIS/>
			<LARGURAFORMULARIO/>
			<MAIUSCULAS>N</MAIUSCULAS>
			<ASSUMIR/>
			<ASSUMIRINTEIRO/>
			<ASSUMIRREAL/>
			<ASSUMIRLOGICO>N</ASSUMIRLOGICO>
			<ASSUMIRDATA/>
			<MINIMO/>
			<MAXIMO/>
			<CAMPOMESTRE/>
			<CAMPOMESTREORIGINAL/>
			<ANCESTRAL/>
			<PESQUISAR/>
			<RESULTADO/>
			<TEXTO/>
			<FLAGS>0</FLAGS>
			<FLAGS1>8</FLAGS1>
			<FLAGS2>0</FLAGS2>
			<CLIDEF>N</CLIDEF>
			<Z_GRUPO/>
			<OBSERVACOES/>
			<PROPRIEDADE>ProcessarComBaseNoSip</PROPRIEDADE>
			<HASH>364F6F9F58FAE1AE83DF7FCE689CF0DF</HASH>
		</BOTAOPROCESSAR>
		<COMPETENCIA>
			<TABELA>SAM_COMPETENCIAPARTOS</TABELA>
			<NOME>COMPETENCIA</NOME>
			<LEGENDAFORMULARIO>Competência</LEGENDAFORMULARIO>
			<LEGENDAGRADE>Competência</LEGENDAGRADE>
			<ORDEM>010</ORDEM>
			<DICA>Deve ser informado o ano que serão contabilizados os partos.</DICA>
			<PAGINA/>
			<CODIGOINTERNO/>
			<SISTEMA>N</SISTEMA>
			<OPCIONAL>N</OPCIONAL>
			<INVISIVEL>N</INVISIVEL>
			<SOLEITURA>N</SOLEITURA>
			<NOVALINHA>N</NOVALINHA>
			<MOSTRARGRID>S</MOSTRARGRID>
			<ALCLIENTE>N</ALCLIENTE>
			<CLASSE>1</CLASSE>
			<HERDARPERMISSAO/>
			<LARGURA/>
			<MASCARA/>
			<DECIMAIS/>
			<LARGURAFORMULARIO/>
			<MAIUSCULAS>N</MAIUSCULAS>
			<ASSUMIR/>
			<ASSUMIRINTEIRO/>
			<ASSUMIRREAL/>
			<ASSUMIRLOGICO/>
			<ASSUMIRDATA/>
			<MINIMO/>
			<MAXIMO/>
			<CAMPOMESTRE/>
			<CAMPOMESTREORIGINAL/>
			<ANCESTRAL/>
			<PESQUISAR/>
			<RESULTADO/>
			<TEXTO/>
			<FLAGS>0</FLAGS>
			<FLAGS1>8</FLAGS1>
			<FLAGS2>0</FLAGS2>
			<CLIDEF>N</CLIDEF>
			<Z_GRUPO/>
			<OBSERVACOES/>
			<PROPRIEDADE>Competencia</PROPRIEDADE>
			<HASH>5C74309C82426912CC4FAC817B39A18C</HASH>
		</COMPETENCIA>
		<DATAHORAINCLUSAO>
			<TABELA>SAM_COMPETENCIAPARTOS</TABELA>
			<NOME>DATAHORAINCLUSAO</NOME>
			<LEGENDAFORMULARIO>Data hora inclusão</LEGENDAFORMULARIO>
			<LEGENDAGRADE>Data hora inclusão</LEGENDAGRADE>
			<ORDEM>050</ORDEM>
			<DICA/>
			<PAGINA/>
			<CODIGOINTERNO/>
			<SISTEMA>N</SISTEMA>
			<OPCIONAL>N</OPCIONAL>
			<INVISIVEL>N</INVISIVEL>
			<SOLEITURA>S</SOLEITURA>
			<NOVALINHA>N</NOVALINHA>
			<MOSTRARGRID>S</MOSTRARGRID>
			<ALCLIENTE>N</ALCLIENTE>
			<CLASSE>5</CLASSE>
			<HERDARPERMISSAO/>
			<LARGURA/>
			<MASCARA/>
			<DECIMAIS/>
			<LARGURAFORMULARIO/>
			<MAIUSCULAS>N</MAIUSCULAS>
			<ASSUMIR/>
			<ASSUMIRINTEIRO/>
			<ASSUMIRREAL/>
			<ASSUMIRLOGICO/>
			<ASSUMIRDATA/>
			<MINIMO/>
			<MAXIMO/>
			<CAMPOMESTRE/>
			<CAMPOMESTREORIGINAL/>
			<ANCESTRAL/>
			<PESQUISAR/>
			<RESULTADO/>
			<TEXTO/>
			<FLAGS>4224</FLAGS>
			<FLAGS1>8</FLAGS1>
			<FLAGS2>0</FLAGS2>
			<CLIDEF>N</CLIDEF>
			<Z_GRUPO/>
			<OBSERVACOES/>
			<PROPRIEDADE>DataHoraInclusao</PROPRIEDADE>
			<HASH>F3570A7F575EE75D1B87028A81542DF1</HASH>
		</DATAHORAINCLUSAO>
		<TOTALPARTOSCESAREAS>
			<TABELA>SAM_COMPETENCIAPARTOS</TABELA>
			<NOME>TOTALPARTOSCESAREAS</NOME>
			<LEGENDAFORMULARIO>Total partos cesáreas</LEGENDAFORMULARIO>
			<LEGENDAGRADE>Total partos cesáreas</LEGENDAGRADE>
			<ORDEM>030</ORDEM>
			<DICA/>
			<PAGINA/>
			<CODIGOINTERNO/>
			<SISTEMA>N</SISTEMA>
			<OPCIONAL>S</OPCIONAL>
			<INVISIVEL>N</INVISIVEL>
			<SOLEITURA>N</SOLEITURA>
			<NOVALINHA>N</NOVALINHA>
			<MOSTRARGRID>S</MOSTRARGRID>
			<ALCLIENTE>N</ALCLIENTE>
			<CLASSE>1</CLASSE>
			<HERDARPERMISSAO/>
			<LARGURA/>
			<MASCARA/>
			<DECIMAIS/>
			<LARGURAFORMULARIO/>
			<MAIUSCULAS>N</MAIUSCULAS>
			<ASSUMIR/>
			<ASSUMIRINTEIRO/>
			<ASSUMIRREAL/>
			<ASSUMIRLOGICO/>
			<ASSUMIRDATA/>
			<MINIMO/>
			<MAXIMO/>
			<CAMPOMESTRE/>
			<CAMPOMESTREORIGINAL/>
			<ANCESTRAL/>
			<PESQUISAR/>
			<RESULTADO/>
			<TEXTO/>
			<FLAGS>0</FLAGS>
			<FLAGS1>8</FLAGS1>
			<FLAGS2>0</FLAGS2>
			<CLIDEF>N</CLIDEF>
			<Z_GRUPO/>
			<OBSERVACOES/>
			<PROPRIEDADE>TotalPartosCesareas</PROPRIEDADE>
			<HASH>EA10C36F54574EC8E498A0720F7592B5</HASH>
		</TOTALPARTOSCESAREAS>
		<TOTALPARTOSNORMAIS>
			<TABELA>SAM_COMPETENCIAPARTOS</TABELA>
			<NOME>TOTALPARTOSNORMAIS</NOME>
			<LEGENDAFORMULARIO>Total partos normais</LEGENDAFORMULARIO>
			<LEGENDAGRADE>Total partos normais</LEGENDAGRADE>
			<ORDEM>020</ORDEM>
			<DICA/>
			<PAGINA/>
			<CODIGOINTERNO/>
			<SISTEMA>N</SISTEMA>
			<OPCIONAL>S</OPCIONAL>
			<INVISIVEL>N</INVISIVEL>
			<SOLEITURA>N</SOLEITURA>
			<NOVALINHA>N</NOVALINHA>
			<MOSTRARGRID>S</MOSTRARGRID>
			<ALCLIENTE>N</ALCLIENTE>
			<CLASSE>1</CLASSE>
			<HERDARPERMISSAO/>
			<LARGURA/>
			<MASCARA/>
			<DECIMAIS/>
			<LARGURAFORMULARIO/>
			<MAIUSCULAS>N</MAIUSCULAS>
			<ASSUMIR/>
			<ASSUMIRINTEIRO/>
			<ASSUMIRREAL/>
			<ASSUMIRLOGICO/>
			<ASSUMIRDATA/>
			<MINIMO/>
			<MAXIMO/>
			<CAMPOMESTRE/>
			<CAMPOMESTREORIGINAL/>
			<ANCESTRAL/>
			<PESQUISAR/>
			<RESULTADO/>
			<TEXTO/>
			<FLAGS>0</FLAGS>
			<FLAGS1>8</FLAGS1>
			<FLAGS2>0</FLAGS2>
			<CLIDEF>N</CLIDEF>
			<Z_GRUPO/>
			<OBSERVACOES/>
			<PROPRIEDADE>TotalPartosNormais</PROPRIEDADE>
			<HASH>88E633FAD18041DB382DECD21837E2ED</HASH>
		</TOTALPARTOSNORMAIS>
		<USUARIOINCLUSAO>
			<TABELA>SAM_COMPETENCIAPARTOS</TABELA>
			<NOME>USUARIOINCLUSAO</NOME>
			<LEGENDAFORMULARIO>Usuário inclusão</LEGENDAFORMULARIO>
			<LEGENDAGRADE>Usuário inclusão</LEGENDAGRADE>
			<ORDEM>040</ORDEM>
			<DICA/>
			<PAGINA/>
			<CODIGOINTERNO/>
			<SISTEMA>N</SISTEMA>
			<OPCIONAL>S</OPCIONAL>
			<INVISIVEL>N</INVISIVEL>
			<SOLEITURA>S</SOLEITURA>
			<NOVALINHA>N</NOVALINHA>
			<MOSTRARGRID>S</MOSTRARGRID>
			<ALCLIENTE>N</ALCLIENTE>
			<CLASSE>6</CLASSE>
			<HERDARPERMISSAO/>
			<LARGURA/>
			<MASCARA/>
			<DECIMAIS/>
			<LARGURAFORMULARIO/>
			<MAIUSCULAS>N</MAIUSCULAS>
			<ASSUMIR/>
			<ASSUMIRINTEIRO/>
			<ASSUMIRREAL/>
			<ASSUMIRLOGICO/>
			<ASSUMIRDATA/>
			<MINIMO/>
			<MAXIMO/>
			<CAMPOMESTRE/>
			<CAMPOMESTREORIGINAL/>
			<ANCESTRAL/>
			<PESQUISAR>Z_GRUPOUSUARIOS</PESQUISAR>
			<RESULTADO>Z_GRUPOUSUARIOS|APELIDO</RESULTADO>
			<TEXTO/>
			<FLAGS>4096</FLAGS>
			<FLAGS1>8</FLAGS1>
			<FLAGS2>0</FLAGS2>
			<CLIDEF>N</CLIDEF>
			<Z_GRUPO/>
			<OBSERVACOES/>
			<PROPRIEDADE>UsuarioInclusao</PROPRIEDADE>
			<HASH>758D41BF6529B4BFD02502F20F7AD3DF</HASH>
		</USUARIOINCLUSAO>
	</Campos>
</Tabela>
