<?xml version="1.0"?>
<Tabela>
	<Configuracoes>
		<HASH>4F113C9FE1530A44949DE329C879001F</HASH>
		<NOME>SAM_AUDITORIA_EVENTO</NOME>
		<APELIDO>ATE0070</APELIDO>
		<LEGENDA>SAM_AUDITORIA_EVENTO</LEGENDA>
		<LOCAL>N</LOCAL>
		<TIPO>N</TIPO>
		<GENERICA>N</GENERICA>
		<DESENVOLVIMENTO>N</DESENVOLVIMENTO>
		<SOLEITURA>N</SOLEITURA>
		<PROTEGERREGISTRO>N</PROTEGERREGISTRO>
		<POREMPRESA>N</POREMPRESA>
		<PORPERIODO>N</PORPERIODO>
		<PORFILIAL>N</PORFILIAL>
		<AGENDA>N</AGENDA>
		<CODIGOINTERNO>0</CODIGOINTERNO>
		<CLIDEF>N</CLIDEF>
		<FLAGS>0</FLAGS>
		<CHAVEDB2EEE/>
		<TOPICOAJUDA>Site: 9907</TOPICOAJUDA>
		<TSPACE/>
		<TSPACELONG/>
		<TSPACEINDEX/>
		<Z_GRUPO/>
		<OBSERVACOES>{\rtf1\ansi\deff0{\fonttbl{\f0\fnil\fcharset0 MS Sans Serif;}}
\viewkind4\uc1\pard\lang1046\f0\fs16 Eventos considerados na auditoria
\par }</OBSERVACOES>
		<TABELAFISICA/>
		<TIPOPARTICIONAMENTO>1</TIPOPARTICIONAMENTO>
		<ORIGEM>1</ORIGEM>
		<COMANDO/>
		<Z_EXCLUIDO/>
		<ENTIDADE>SamAuditoriaEvento</ENTIDADE>
	</Configuracoes>
	<Campos>
		<ACAOPAGAMENTO>
			<TABELA>SAM_AUDITORIA_EVENTO</TABELA>
			<NOME>ACAOPAGAMENTO</NOME>
			<LEGENDAFORMULARIO>Ação pagamento</LEGENDAFORMULARIO>
			<LEGENDAGRADE/>
			<ORDEM>070</ORDEM>
			<DICA/>
			<PAGINA/>
			<CODIGOINTERNO/>
			<SISTEMA>N</SISTEMA>
			<OPCIONAL>N</OPCIONAL>
			<INVISIVEL>N</INVISIVEL>
			<SOLEITURA>N</SOLEITURA>
			<NOVALINHA>N</NOVALINHA>
			<MOSTRARGRID>S</MOSTRARGRID>
			<ALCLIENTE>N</ALCLIENTE>
			<CLASSE>18</CLASSE>
			<HERDARPERMISSAO/>
			<LARGURA>3</LARGURA>
			<MASCARA/>
			<DECIMAIS/>
			<LARGURAFORMULARIO/>
			<MAIUSCULAS>N</MAIUSCULAS>
			<ASSUMIR/>
			<ASSUMIRINTEIRO/>
			<ASSUMIRREAL/>
			<ASSUMIRLOGICO>N</ASSUMIRLOGICO>
			<ASSUMIRDATA/>
			<MINIMO/>
			<MAXIMO/>
			<CAMPOMESTRE/>
			<CAMPOMESTREORIGINAL/>
			<ANCESTRAL/>
			<PESQUISAR/>
			<RESULTADO/>
			<TEXTO>1#Glosar|G|S|Observar|O|S|Pagar|P|S|</TEXTO>
			<FLAGS>0</FLAGS>
			<FLAGS1>8</FLAGS1>
			<FLAGS2>1</FLAGS2>
			<CLIDEF>N</CLIDEF>
			<Z_GRUPO/>
			<OBSERVACOES/>
			<PROPRIEDADE/>
			<HASH>CC37022C0A7FBD3E0213E4E20CE8A713</HASH>
		</ACAOPAGAMENTO>
		<AUDITORIA>
			<TABELA>SAM_AUDITORIA_EVENTO</TABELA>
			<NOME>AUDITORIA</NOME>
			<LEGENDAFORMULARIO>Auditoria</LEGENDAFORMULARIO>
			<LEGENDAGRADE>Auditoria</LEGENDAGRADE>
			<ORDEM>050</ORDEM>
			<DICA>Auditoria do evento</DICA>
			<PAGINA/>
			<CODIGOINTERNO/>
			<SISTEMA>N</SISTEMA>
			<OPCIONAL>N</OPCIONAL>
			<INVISIVEL>S</INVISIVEL>
			<SOLEITURA>N</SOLEITURA>
			<NOVALINHA>N</NOVALINHA>
			<MOSTRARGRID>S</MOSTRARGRID>
			<ALCLIENTE>N</ALCLIENTE>
			<CLASSE>6</CLASSE>
			<HERDARPERMISSAO/>
			<LARGURA/>
			<MASCARA/>
			<DECIMAIS/>
			<LARGURAFORMULARIO/>
			<MAIUSCULAS>N</MAIUSCULAS>
			<ASSUMIR/>
			<ASSUMIRINTEIRO/>
			<ASSUMIRREAL/>
			<ASSUMIRLOGICO>N</ASSUMIRLOGICO>
			<ASSUMIRDATA/>
			<MINIMO/>
			<MAXIMO/>
			<CAMPOMESTRE/>
			<CAMPOMESTREORIGINAL/>
			<ANCESTRAL/>
			<PESQUISAR>SAM_AUDITORIA</PESQUISAR>
			<RESULTADO>SAM_AUDITORIA|AUDITORIA</RESULTADO>
			<TEXTO/>
			<FLAGS>0</FLAGS>
			<FLAGS1>8</FLAGS1>
			<FLAGS2>0</FLAGS2>
			<CLIDEF>N</CLIDEF>
			<Z_GRUPO/>
			<OBSERVACOES/>
			<PROPRIEDADE/>
			<HASH>4FAEF33E91E9B35CB9D4480D7F5EF275</HASH>
		</AUDITORIA>
		<CODIGOGLOSATISS>
			<TABELA>SAM_AUDITORIA_EVENTO</TABELA>
			<NOME>CODIGOGLOSATISS</NOME>
			<LEGENDAFORMULARIO>Código glosa TISS</LEGENDAFORMULARIO>
			<LEGENDAGRADE>Código glosa TISS</LEGENDAGRADE>
			<ORDEM>085</ORDEM>
			<DICA>Código glosa TISS</DICA>
			<PAGINA/>
			<CODIGOINTERNO/>
			<SISTEMA>N</SISTEMA>
			<OPCIONAL>S</OPCIONAL>
			<INVISIVEL>N</INVISIVEL>
			<SOLEITURA>N</SOLEITURA>
			<NOVALINHA>S</NOVALINHA>
			<MOSTRARGRID>S</MOSTRARGRID>
			<ALCLIENTE>N</ALCLIENTE>
			<CLASSE>17</CLASSE>
			<HERDARPERMISSAO/>
			<LARGURA>50</LARGURA>
			<MASCARA/>
			<DECIMAIS/>
			<LARGURAFORMULARIO/>
			<MAIUSCULAS>N</MAIUSCULAS>
			<ASSUMIR/>
			<ASSUMIRINTEIRO/>
			<ASSUMIRREAL/>
			<ASSUMIRLOGICO>N</ASSUMIRLOGICO>
			<ASSUMIRDATA/>
			<MINIMO/>
			<MAXIMO/>
			<CAMPOMESTRE/>
			<CAMPOMESTREORIGINAL/>
			<ANCESTRAL/>
			<PESQUISAR/>
			<RESULTADO/>
			<TEXTO>MOTIVOGLOSA|CODIGOGLOSATISS|CODIGOGLOSATISS+' - '+DESCRICAOGLOSATISS</TEXTO>
			<FLAGS>0</FLAGS>
			<FLAGS1>8</FLAGS1>
			<FLAGS2>0</FLAGS2>
			<CLIDEF>N</CLIDEF>
			<Z_GRUPO/>
			<OBSERVACOES/>
			<PROPRIEDADE/>
			<HASH>E420C621C75116590BEFF3022F1FB144</HASH>
		</CODIGOGLOSATISS>
		<EVENTOGERADO>
			<TABELA>SAM_AUDITORIA_EVENTO</TABELA>
			<NOME>EVENTOGERADO</NOME>
			<LEGENDAFORMULARIO>Evento gerado</LEGENDAFORMULARIO>
			<LEGENDAGRADE>Evento gerado</LEGENDAGRADE>
			<ORDEM>060</ORDEM>
			<DICA>Evento da auditoria</DICA>
			<PAGINA/>
			<CODIGOINTERNO/>
			<SISTEMA>N</SISTEMA>
			<OPCIONAL>N</OPCIONAL>
			<INVISIVEL>N</INVISIVEL>
			<SOLEITURA>N</SOLEITURA>
			<NOVALINHA>N</NOVALINHA>
			<MOSTRARGRID>S</MOSTRARGRID>
			<ALCLIENTE>N</ALCLIENTE>
			<CLASSE>6</CLASSE>
			<HERDARPERMISSAO/>
			<LARGURA/>
			<MASCARA/>
			<DECIMAIS/>
			<LARGURAFORMULARIO/>
			<MAIUSCULAS>N</MAIUSCULAS>
			<ASSUMIR/>
			<ASSUMIRINTEIRO/>
			<ASSUMIRREAL/>
			<ASSUMIRLOGICO>N</ASSUMIRLOGICO>
			<ASSUMIRDATA/>
			<MINIMO/>
			<MAXIMO/>
			<CAMPOMESTRE/>
			<CAMPOMESTREORIGINAL/>
			<ANCESTRAL/>
			<PESQUISAR>SAM_AUTORIZ_EVENTOGERADO</PESQUISAR>
			<RESULTADO>SAM_AUTORIZ_EVENTOGERADO|EVENTOGERADO</RESULTADO>
			<TEXTO/>
			<FLAGS>4096</FLAGS>
			<FLAGS1>8</FLAGS1>
			<FLAGS2>0</FLAGS2>
			<CLIDEF>N</CLIDEF>
			<Z_GRUPO/>
			<OBSERVACOES/>
			<PROPRIEDADE/>
			<HASH>C5F7B2099D510392CFF2564114D07C03</HASH>
		</EVENTOGERADO>
		<MOTIVOGLOSA>
			<TABELA>SAM_AUDITORIA_EVENTO</TABELA>
			<NOME>MOTIVOGLOSA</NOME>
			<LEGENDAFORMULARIO>Motivo Glosa</LEGENDAFORMULARIO>
			<LEGENDAGRADE>Motivo Glosa</LEGENDAGRADE>
			<ORDEM>080</ORDEM>
			<DICA>Motivo glosa</DICA>
			<PAGINA/>
			<CODIGOINTERNO/>
			<SISTEMA>N</SISTEMA>
			<OPCIONAL>S</OPCIONAL>
			<INVISIVEL>N</INVISIVEL>
			<SOLEITURA>N</SOLEITURA>
			<NOVALINHA>N</NOVALINHA>
			<MOSTRARGRID>S</MOSTRARGRID>
			<ALCLIENTE>N</ALCLIENTE>
			<CLASSE>6</CLASSE>
			<HERDARPERMISSAO/>
			<LARGURA/>
			<MASCARA/>
			<DECIMAIS/>
			<LARGURAFORMULARIO/>
			<MAIUSCULAS>N</MAIUSCULAS>
			<ASSUMIR/>
			<ASSUMIRINTEIRO/>
			<ASSUMIRREAL/>
			<ASSUMIRLOGICO>N</ASSUMIRLOGICO>
			<ASSUMIRDATA/>
			<MINIMO/>
			<MAXIMO/>
			<CAMPOMESTRE/>
			<CAMPOMESTREORIGINAL/>
			<ANCESTRAL/>
			<PESQUISAR>SAM_MOTIVOGLOSA</PESQUISAR>
			<RESULTADO>SAM_MOTIVOGLOSA|DESCRICAO</RESULTADO>
			<TEXTO>ATIVA='S'</TEXTO>
			<FLAGS>0</FLAGS>
			<FLAGS1>8</FLAGS1>
			<FLAGS2>0</FLAGS2>
			<CLIDEF>N</CLIDEF>
			<Z_GRUPO/>
			<OBSERVACOES/>
			<PROPRIEDADE/>
			<HASH>4DDA9289BD3DC3876AE2AD5CCF7E12A1</HASH>
		</MOTIVOGLOSA>
		<OBSERVACOES>
			<TABELA>SAM_AUDITORIA_EVENTO</TABELA>
			<NOME>OBSERVACOES</NOME>
			<LEGENDAFORMULARIO>Observações</LEGENDAFORMULARIO>
			<LEGENDAGRADE>Observações</LEGENDAGRADE>
			<ORDEM>090</ORDEM>
			<DICA/>
			<PAGINA/>
			<CODIGOINTERNO/>
			<SISTEMA>N</SISTEMA>
			<OPCIONAL>S</OPCIONAL>
			<INVISIVEL>N</INVISIVEL>
			<SOLEITURA>N</SOLEITURA>
			<NOVALINHA>N</NOVALINHA>
			<MOSTRARGRID>S</MOSTRARGRID>
			<ALCLIENTE>N</ALCLIENTE>
			<CLASSE>0</CLASSE>
			<HERDARPERMISSAO/>
			<LARGURA>250</LARGURA>
			<MASCARA/>
			<DECIMAIS/>
			<LARGURAFORMULARIO/>
			<MAIUSCULAS>N</MAIUSCULAS>
			<ASSUMIR/>
			<ASSUMIRINTEIRO/>
			<ASSUMIRREAL/>
			<ASSUMIRLOGICO>N</ASSUMIRLOGICO>
			<ASSUMIRDATA/>
			<MINIMO/>
			<MAXIMO>4</MAXIMO>
			<CAMPOMESTRE/>
			<CAMPOMESTREORIGINAL/>
			<ANCESTRAL/>
			<PESQUISAR/>
			<RESULTADO/>
			<TEXTO/>
			<FLAGS>0</FLAGS>
			<FLAGS1>8</FLAGS1>
			<FLAGS2>0</FLAGS2>
			<CLIDEF>N</CLIDEF>
			<Z_GRUPO/>
			<OBSERVACOES/>
			<PROPRIEDADE/>
			<HASH>285D6357C6CC61503EBCB3942C091CC9</HASH>
		</OBSERVACOES>
	</Campos>
	<Indices>
		<AUDITORIA_virgula__t_EVENTOGERADO>
			<Z_GRUPO/>
			<UNICO>S</UNICO>
			<CAMPOS>AUDITORIA, EVENTOGERADO</CAMPOS>
			<CLIDEF>N</CLIDEF>
			<FLAGS>0</FLAGS>
			<AUTOMATICO>N</AUTOMATICO>
			<EXCLUIDO>N</EXCLUIDO>
			<FUNCAO/>
			<DEFINICAOMANUAL/>
			<HASH>88A6EDB0D63CAFB6E33C0932FE1DB75C</HASH>
		</AUDITORIA_virgula__t_EVENTOGERADO>
	</Indices>
</Tabela>
