<?xml version="1.0"?>
<Tabela>
	<Configuracoes>
		<HASH>C8DB40350595FAAA2C4AD37E846CA44D</HASH>
		<NOME>SAM_PRECOGERALREGIME_FX</NOME>
		<APELIDO/>
		<LEGENDA>SAM_PRECOGERALREGIME_FX</LEGENDA>
		<LOCAL>N</LOCAL>
		<TIPO>N</TIPO>
		<GENERICA>N</GENERICA>
		<DESENVOLVIMENTO>N</DESENVOLVIMENTO>
		<SOLEITURA>N</SOLEITURA>
		<PROTEGERREGISTRO>N</PROTEGERREGISTRO>
		<POREMPRESA>N</POREMPRESA>
		<PORPERIODO>N</PORPERIODO>
		<PORFILIAL>N</PORFILIAL>
		<AGENDA>N</AGENDA>
		<CODIGOINTERNO>0</CODIGOINTERNO>
		<CLIDEF>N</CLIDEF>
		<FLAGS>0</FLAGS>
		<CHAVEDB2EEE/>
		<TOPICOAJUDA>Site: 9907</TOPICOAJUDA>
		<TSPACE/>
		<TSPACELONG/>
		<TSPACEINDEX/>
		<Z_GRUPO/>
		<OBSERVACOES>{\rtf1\ansi\deff0{\fonttbl{\f0\fnil\fcharset0 MS Sans Serif;}}
\viewkind4\uc1\pard\lang1046\f0\fs16 Parametriza\'e7\'e3o de Pre\'e7o Geral de evento por Regime de Atendimento e Faixa de Eventos
\par }</OBSERVACOES>
		<TABELAFISICA/>
		<TIPOPARTICIONAMENTO>1</TIPOPARTICIONAMENTO>
		<ORIGEM>1</ORIGEM>
		<COMANDO/>
		<Z_EXCLUIDO/>
		<ENTIDADE>SamPrecoGeralRegimeFx</ENTIDADE>
	</Configuracoes>
	<Campos>
		<BOTAOVALORES>
			<TABELA>SAM_PRECOGERALREGIME_FX</TABELA>
			<NOME>BOTAOVALORES</NOME>
			<LEGENDAFORMULARIO>Valores</LEGENDAFORMULARIO>
			<LEGENDAGRADE>Valores</LEGENDAGRADE>
			<ORDEM>080</ORDEM>
			<DICA>Visualizar os valores da faixa de eventos</DICA>
			<PAGINA/>
			<CODIGOINTERNO/>
			<SISTEMA>N</SISTEMA>
			<OPCIONAL>N</OPCIONAL>
			<INVISIVEL>N</INVISIVEL>
			<SOLEITURA>N</SOLEITURA>
			<NOVALINHA>N</NOVALINHA>
			<MOSTRARGRID>S</MOSTRARGRID>
			<ALCLIENTE>N</ALCLIENTE>
			<CLASSE>11</CLASSE>
			<HERDARPERMISSAO/>
			<LARGURA/>
			<MASCARA/>
			<DECIMAIS/>
			<LARGURAFORMULARIO/>
			<MAIUSCULAS>N</MAIUSCULAS>
			<ASSUMIR/>
			<ASSUMIRINTEIRO/>
			<ASSUMIRREAL/>
			<ASSUMIRLOGICO>N</ASSUMIRLOGICO>
			<ASSUMIRDATA/>
			<MINIMO/>
			<MAXIMO/>
			<CAMPOMESTRE/>
			<CAMPOMESTREORIGINAL/>
			<ANCESTRAL/>
			<PESQUISAR/>
			<RESULTADO/>
			<TEXTO/>
			<FLAGS>0</FLAGS>
			<FLAGS1>8</FLAGS1>
			<FLAGS2>0</FLAGS2>
			<CLIDEF>N</CLIDEF>
			<Z_GRUPO/>
			<OBSERVACOES/>
			<PROPRIEDADE/>
			<HASH>C4B90EA3192776100A2C1CC05A5ECC10</HASH>
		</BOTAOVALORES>
		<CONVENIO>
			<TABELA>SAM_PRECOGERALREGIME_FX</TABELA>
			<NOME>CONVENIO</NOME>
			<LEGENDAFORMULARIO>Convênio</LEGENDAFORMULARIO>
			<LEGENDAGRADE>Convênio</LEGENDAGRADE>
			<ORDEM>095</ORDEM>
			<DICA>Convênio para o preço</DICA>
			<PAGINA/>
			<CODIGOINTERNO/>
			<SISTEMA>N</SISTEMA>
			<OPCIONAL>N</OPCIONAL>
			<INVISIVEL>N</INVISIVEL>
			<SOLEITURA>N</SOLEITURA>
			<NOVALINHA>S</NOVALINHA>
			<MOSTRARGRID>S</MOSTRARGRID>
			<ALCLIENTE>N</ALCLIENTE>
			<CLASSE>6</CLASSE>
			<HERDARPERMISSAO/>
			<LARGURA/>
			<MASCARA/>
			<DECIMAIS/>
			<LARGURAFORMULARIO/>
			<MAIUSCULAS>N</MAIUSCULAS>
			<ASSUMIR/>
			<ASSUMIRINTEIRO/>
			<ASSUMIRREAL/>
			<ASSUMIRLOGICO/>
			<ASSUMIRDATA/>
			<MINIMO/>
			<MAXIMO/>
			<CAMPOMESTRE/>
			<CAMPOMESTREORIGINAL/>
			<ANCESTRAL/>
			<PESQUISAR>SAM_CONVENIO</PESQUISAR>
			<RESULTADO>SAM_CONVENIO|DESCRICAO</RESULTADO>
			<TEXTO/>
			<FLAGS>4096</FLAGS>
			<FLAGS1>8</FLAGS1>
			<FLAGS2>0</FLAGS2>
			<CLIDEF>N</CLIDEF>
			<Z_GRUPO/>
			<OBSERVACOES/>
			<PROPRIEDADE/>
			<HASH>DC300E72DA11DAD4A8F56539C3A37527</HASH>
		</CONVENIO>
		<DATAFINAL>
			<TABELA>SAM_PRECOGERALREGIME_FX</TABELA>
			<NOME>DATAFINAL</NOME>
			<LEGENDAFORMULARIO>Data final</LEGENDAFORMULARIO>
			<LEGENDAGRADE>Data final</LEGENDAGRADE>
			<ORDEM>140</ORDEM>
			<DICA>Data Final da vigência do preço</DICA>
			<PAGINA/>
			<CODIGOINTERNO/>
			<SISTEMA>N</SISTEMA>
			<OPCIONAL>S</OPCIONAL>
			<INVISIVEL>N</INVISIVEL>
			<SOLEITURA>N</SOLEITURA>
			<NOVALINHA>N</NOVALINHA>
			<MOSTRARGRID>S</MOSTRARGRID>
			<ALCLIENTE>N</ALCLIENTE>
			<CLASSE>5</CLASSE>
			<HERDARPERMISSAO/>
			<LARGURA/>
			<MASCARA/>
			<DECIMAIS/>
			<LARGURAFORMULARIO/>
			<MAIUSCULAS>N</MAIUSCULAS>
			<ASSUMIR/>
			<ASSUMIRINTEIRO/>
			<ASSUMIRREAL/>
			<ASSUMIRLOGICO>N</ASSUMIRLOGICO>
			<ASSUMIRDATA/>
			<MINIMO/>
			<MAXIMO/>
			<CAMPOMESTRE/>
			<CAMPOMESTREORIGINAL/>
			<ANCESTRAL/>
			<PESQUISAR/>
			<RESULTADO/>
			<TEXTO/>
			<FLAGS>128</FLAGS>
			<FLAGS1>8</FLAGS1>
			<FLAGS2>0</FLAGS2>
			<CLIDEF>N</CLIDEF>
			<Z_GRUPO/>
			<OBSERVACOES/>
			<PROPRIEDADE/>
			<HASH>BA0968E3EA7B92E5A82700455B626A8E</HASH>
		</DATAFINAL>
		<DATAINICIAL>
			<TABELA>SAM_PRECOGERALREGIME_FX</TABELA>
			<NOME>DATAINICIAL</NOME>
			<LEGENDAFORMULARIO>Data inicial</LEGENDAFORMULARIO>
			<LEGENDAGRADE>Data inicial</LEGENDAGRADE>
			<ORDEM>130</ORDEM>
			<DICA>Data Inicial da vigência do preço</DICA>
			<PAGINA/>
			<CODIGOINTERNO/>
			<SISTEMA>N</SISTEMA>
			<OPCIONAL>N</OPCIONAL>
			<INVISIVEL>N</INVISIVEL>
			<SOLEITURA>N</SOLEITURA>
			<NOVALINHA>S</NOVALINHA>
			<MOSTRARGRID>S</MOSTRARGRID>
			<ALCLIENTE>N</ALCLIENTE>
			<CLASSE>5</CLASSE>
			<HERDARPERMISSAO/>
			<LARGURA/>
			<MASCARA/>
			<DECIMAIS/>
			<LARGURAFORMULARIO/>
			<MAIUSCULAS>N</MAIUSCULAS>
			<ASSUMIR/>
			<ASSUMIRINTEIRO/>
			<ASSUMIRREAL/>
			<ASSUMIRLOGICO>N</ASSUMIRLOGICO>
			<ASSUMIRDATA/>
			<MINIMO/>
			<MAXIMO/>
			<CAMPOMESTRE/>
			<CAMPOMESTREORIGINAL/>
			<ANCESTRAL/>
			<PESQUISAR/>
			<RESULTADO/>
			<TEXTO/>
			<FLAGS>640</FLAGS>
			<FLAGS1>8</FLAGS1>
			<FLAGS2>0</FLAGS2>
			<CLIDEF>N</CLIDEF>
			<Z_GRUPO/>
			<OBSERVACOES/>
			<PROPRIEDADE/>
			<HASH>2397AC6C1962AE638DE835BC68F1ABCB</HASH>
		</DATAINICIAL>
		<ESTRUTURAFINAL>
			<TABELA>SAM_PRECOGERALREGIME_FX</TABELA>
			<NOME>ESTRUTURAFINAL</NOME>
			<LEGENDAFORMULARIO>Estrutura final</LEGENDAFORMULARIO>
			<LEGENDAGRADE>Estrutura final</LEGENDAGRADE>
			<ORDEM>122</ORDEM>
			<DICA>Estrutura do evento final</DICA>
			<PAGINA/>
			<CODIGOINTERNO/>
			<SISTEMA>N</SISTEMA>
			<OPCIONAL>S</OPCIONAL>
			<INVISIVEL>N</INVISIVEL>
			<SOLEITURA>S</SOLEITURA>
			<NOVALINHA>N</NOVALINHA>
			<MOSTRARGRID>S</MOSTRARGRID>
			<ALCLIENTE>N</ALCLIENTE>
			<CLASSE>0</CLASSE>
			<HERDARPERMISSAO/>
			<LARGURA>20</LARGURA>
			<MASCARA/>
			<DECIMAIS/>
			<LARGURAFORMULARIO/>
			<MAIUSCULAS>N</MAIUSCULAS>
			<ASSUMIR/>
			<ASSUMIRINTEIRO/>
			<ASSUMIRREAL/>
			<ASSUMIRLOGICO>N</ASSUMIRLOGICO>
			<ASSUMIRDATA/>
			<MINIMO/>
			<MAXIMO/>
			<CAMPOMESTRE/>
			<CAMPOMESTREORIGINAL/>
			<ANCESTRAL/>
			<PESQUISAR/>
			<RESULTADO/>
			<TEXTO/>
			<FLAGS>0</FLAGS>
			<FLAGS1>8</FLAGS1>
			<FLAGS2>0</FLAGS2>
			<CLIDEF>N</CLIDEF>
			<Z_GRUPO/>
			<OBSERVACOES/>
			<PROPRIEDADE/>
			<HASH>9A92A1FF503863037176161432FCB72B</HASH>
		</ESTRUTURAFINAL>
		<ESTRUTURAINICIAL>
			<TABELA>SAM_PRECOGERALREGIME_FX</TABELA>
			<NOME>ESTRUTURAINICIAL</NOME>
			<LEGENDAFORMULARIO>Estrutura inicial</LEGENDAFORMULARIO>
			<LEGENDAGRADE>Estrutura inicial</LEGENDAGRADE>
			<ORDEM>112</ORDEM>
			<DICA>Estrutura do evento inicial</DICA>
			<PAGINA/>
			<CODIGOINTERNO/>
			<SISTEMA>N</SISTEMA>
			<OPCIONAL>S</OPCIONAL>
			<INVISIVEL>N</INVISIVEL>
			<SOLEITURA>S</SOLEITURA>
			<NOVALINHA>N</NOVALINHA>
			<MOSTRARGRID>S</MOSTRARGRID>
			<ALCLIENTE>N</ALCLIENTE>
			<CLASSE>0</CLASSE>
			<HERDARPERMISSAO/>
			<LARGURA>20</LARGURA>
			<MASCARA/>
			<DECIMAIS/>
			<LARGURAFORMULARIO/>
			<MAIUSCULAS>N</MAIUSCULAS>
			<ASSUMIR/>
			<ASSUMIRINTEIRO/>
			<ASSUMIRREAL/>
			<ASSUMIRLOGICO>N</ASSUMIRLOGICO>
			<ASSUMIRDATA/>
			<MINIMO/>
			<MAXIMO/>
			<CAMPOMESTRE/>
			<CAMPOMESTREORIGINAL/>
			<ANCESTRAL/>
			<PESQUISAR/>
			<RESULTADO/>
			<TEXTO/>
			<FLAGS>0</FLAGS>
			<FLAGS1>8</FLAGS1>
			<FLAGS2>0</FLAGS2>
			<CLIDEF>N</CLIDEF>
			<Z_GRUPO/>
			<OBSERVACOES/>
			<PROPRIEDADE/>
			<HASH>0D39EE716FE70383E1901AA9E4C6F848</HASH>
		</ESTRUTURAINICIAL>
		<EVENTOFINAL>
			<TABELA>SAM_PRECOGERALREGIME_FX</TABELA>
			<NOME>EVENTOFINAL</NOME>
			<LEGENDAFORMULARIO>Evento final</LEGENDAFORMULARIO>
			<LEGENDAGRADE>Evento final</LEGENDAGRADE>
			<ORDEM>120</ORDEM>
			<DICA>Descrição do evento final</DICA>
			<PAGINA/>
			<CODIGOINTERNO/>
			<SISTEMA>N</SISTEMA>
			<OPCIONAL>N</OPCIONAL>
			<INVISIVEL>N</INVISIVEL>
			<SOLEITURA>N</SOLEITURA>
			<NOVALINHA>N</NOVALINHA>
			<MOSTRARGRID>S</MOSTRARGRID>
			<ALCLIENTE>N</ALCLIENTE>
			<CLASSE>6</CLASSE>
			<HERDARPERMISSAO/>
			<LARGURA/>
			<MASCARA/>
			<DECIMAIS/>
			<LARGURAFORMULARIO/>
			<MAIUSCULAS>N</MAIUSCULAS>
			<ASSUMIR/>
			<ASSUMIRINTEIRO/>
			<ASSUMIRREAL/>
			<ASSUMIRLOGICO>N</ASSUMIRLOGICO>
			<ASSUMIRDATA/>
			<MINIMO/>
			<MAXIMO/>
			<CAMPOMESTRE/>
			<CAMPOMESTREORIGINAL/>
			<ANCESTRAL/>
			<PESQUISAR>SAM_TGE</PESQUISAR>
			<RESULTADO>SAM_TGE|DESCRICAO</RESULTADO>
			<TEXTO>INATIVO &lt;&gt; 'S'</TEXTO>
			<FLAGS>4096</FLAGS>
			<FLAGS1>65800</FLAGS1>
			<FLAGS2>0</FLAGS2>
			<CLIDEF>N</CLIDEF>
			<Z_GRUPO/>
			<OBSERVACOES/>
			<PROPRIEDADE/>
			<HASH>BEC16D86D22209E4EFB5A02E6DC1394E</HASH>
		</EVENTOFINAL>
		<EVENTOINICIAL>
			<TABELA>SAM_PRECOGERALREGIME_FX</TABELA>
			<NOME>EVENTOINICIAL</NOME>
			<LEGENDAFORMULARIO>Evento inicial</LEGENDAFORMULARIO>
			<LEGENDAGRADE>Evento inicial</LEGENDAGRADE>
			<ORDEM>110</ORDEM>
			<DICA>Descrição do evento inicial</DICA>
			<PAGINA/>
			<CODIGOINTERNO/>
			<SISTEMA>N</SISTEMA>
			<OPCIONAL>N</OPCIONAL>
			<INVISIVEL>N</INVISIVEL>
			<SOLEITURA>N</SOLEITURA>
			<NOVALINHA>S</NOVALINHA>
			<MOSTRARGRID>S</MOSTRARGRID>
			<ALCLIENTE>N</ALCLIENTE>
			<CLASSE>6</CLASSE>
			<HERDARPERMISSAO/>
			<LARGURA/>
			<MASCARA/>
			<DECIMAIS/>
			<LARGURAFORMULARIO/>
			<MAIUSCULAS>N</MAIUSCULAS>
			<ASSUMIR/>
			<ASSUMIRINTEIRO/>
			<ASSUMIRREAL/>
			<ASSUMIRLOGICO>N</ASSUMIRLOGICO>
			<ASSUMIRDATA/>
			<MINIMO/>
			<MAXIMO/>
			<CAMPOMESTRE/>
			<CAMPOMESTREORIGINAL/>
			<ANCESTRAL/>
			<PESQUISAR>SAM_TGE</PESQUISAR>
			<RESULTADO>SAM_TGE|DESCRICAO</RESULTADO>
			<TEXTO>INATIVO &lt;&gt; 'S'</TEXTO>
			<FLAGS>4096</FLAGS>
			<FLAGS1>65800</FLAGS1>
			<FLAGS2>0</FLAGS2>
			<CLIDEF>N</CLIDEF>
			<Z_GRUPO/>
			<OBSERVACOES/>
			<PROPRIEDADE/>
			<HASH>3C0F3689C3E704E08E59418CEED0C28D</HASH>
		</EVENTOINICIAL>
		<GRUPOVIGENCIA>
			<TABELA>SAM_PRECOGERALREGIME_FX</TABELA>
			<NOME>GRUPOVIGENCIA</NOME>
			<LEGENDAFORMULARIO>Vigência</LEGENDAFORMULARIO>
			<LEGENDAGRADE>Vigência</LEGENDAGRADE>
			<ORDEM>090</ORDEM>
			<DICA>Vigência do Preço</DICA>
			<PAGINA/>
			<CODIGOINTERNO/>
			<SISTEMA>N</SISTEMA>
			<OPCIONAL>N</OPCIONAL>
			<INVISIVEL>N</INVISIVEL>
			<SOLEITURA>N</SOLEITURA>
			<NOVALINHA>N</NOVALINHA>
			<MOSTRARGRID>S</MOSTRARGRID>
			<ALCLIENTE>N</ALCLIENTE>
			<CLASSE>15</CLASSE>
			<HERDARPERMISSAO/>
			<LARGURA/>
			<MASCARA/>
			<DECIMAIS/>
			<LARGURAFORMULARIO/>
			<MAIUSCULAS>N</MAIUSCULAS>
			<ASSUMIR/>
			<ASSUMIRINTEIRO/>
			<ASSUMIRREAL/>
			<ASSUMIRLOGICO>N</ASSUMIRLOGICO>
			<ASSUMIRDATA/>
			<MINIMO/>
			<MAXIMO/>
			<CAMPOMESTRE/>
			<CAMPOMESTREORIGINAL/>
			<ANCESTRAL/>
			<PESQUISAR/>
			<RESULTADO/>
			<TEXTO>1#DATAINICIAL|S|DATAFINAL|S|</TEXTO>
			<FLAGS>0</FLAGS>
			<FLAGS1>8</FLAGS1>
			<FLAGS2>0</FLAGS2>
			<CLIDEF>N</CLIDEF>
			<Z_GRUPO/>
			<OBSERVACOES/>
			<PROPRIEDADE/>
			<HASH>2C518B27B145773C1DFFDBCD15F482C0</HASH>
		</GRUPOVIGENCIA>
		<MASCARATGE>
			<TABELA>SAM_PRECOGERALREGIME_FX</TABELA>
			<NOME>MASCARATGE</NOME>
			<LEGENDAFORMULARIO>Máscara TGE</LEGENDAFORMULARIO>
			<LEGENDAGRADE>Máscara TGE</LEGENDAGRADE>
			<ORDEM>100</ORDEM>
			<DICA>Máscara da TGE a ser utilizada para localizar a tabela genérica</DICA>
			<PAGINA/>
			<CODIGOINTERNO/>
			<SISTEMA>N</SISTEMA>
			<OPCIONAL>N</OPCIONAL>
			<INVISIVEL>N</INVISIVEL>
			<SOLEITURA>N</SOLEITURA>
			<NOVALINHA>S</NOVALINHA>
			<MOSTRARGRID>S</MOSTRARGRID>
			<ALCLIENTE>N</ALCLIENTE>
			<CLASSE>6</CLASSE>
			<HERDARPERMISSAO/>
			<LARGURA/>
			<MASCARA/>
			<DECIMAIS/>
			<LARGURAFORMULARIO/>
			<MAIUSCULAS>N</MAIUSCULAS>
			<ASSUMIR/>
			<ASSUMIRINTEIRO/>
			<ASSUMIRREAL/>
			<ASSUMIRLOGICO/>
			<ASSUMIRDATA/>
			<MINIMO/>
			<MAXIMO/>
			<CAMPOMESTRE/>
			<CAMPOMESTREORIGINAL/>
			<ANCESTRAL/>
			<PESQUISAR>SAM_MASCARATGE</PESQUISAR>
			<RESULTADO>SAM_MASCARATGE|DESCRICAO</RESULTADO>
			<TEXTO/>
			<FLAGS>4096</FLAGS>
			<FLAGS1>8</FLAGS1>
			<FLAGS2>0</FLAGS2>
			<CLIDEF>N</CLIDEF>
			<Z_GRUPO/>
			<OBSERVACOES/>
			<PROPRIEDADE/>
			<HASH>F6364A57A7CE0808EFCBDDB37DA9D5AF</HASH>
		</MASCARATGE>
		<OBSERVACAO>
			<TABELA>SAM_PRECOGERALREGIME_FX</TABELA>
			<NOME>OBSERVACAO</NOME>
			<LEGENDAFORMULARIO>Observação</LEGENDAFORMULARIO>
			<LEGENDAGRADE>Observação</LEGENDAGRADE>
			<ORDEM>190</ORDEM>
			<DICA>Observação da faixa de eventos</DICA>
			<PAGINA/>
			<CODIGOINTERNO/>
			<SISTEMA>N</SISTEMA>
			<OPCIONAL>S</OPCIONAL>
			<INVISIVEL>N</INVISIVEL>
			<SOLEITURA>N</SOLEITURA>
			<NOVALINHA>N</NOVALINHA>
			<MOSTRARGRID>S</MOSTRARGRID>
			<ALCLIENTE>N</ALCLIENTE>
			<CLASSE>7</CLASSE>
			<HERDARPERMISSAO/>
			<LARGURA>11</LARGURA>
			<MASCARA/>
			<DECIMAIS/>
			<LARGURAFORMULARIO/>
			<MAIUSCULAS>N</MAIUSCULAS>
			<ASSUMIR/>
			<ASSUMIRINTEIRO>3689</ASSUMIRINTEIRO>
			<ASSUMIRREAL/>
			<ASSUMIRLOGICO>N</ASSUMIRLOGICO>
			<ASSUMIRDATA/>
			<MINIMO/>
			<MAXIMO/>
			<CAMPOMESTRE/>
			<CAMPOMESTREORIGINAL/>
			<ANCESTRAL/>
			<PESQUISAR/>
			<RESULTADO/>
			<TEXTO/>
			<FLAGS>65536</FLAGS>
			<FLAGS1>524300</FLAGS1>
			<FLAGS2>0</FLAGS2>
			<CLIDEF>N</CLIDEF>
			<Z_GRUPO/>
			<OBSERVACOES/>
			<PROPRIEDADE/>
			<HASH>446C8B13214F3739A592110350A092DE</HASH>
		</OBSERVACAO>
		<ORIGEMEVENTO>
			<TABELA>SAM_PRECOGERALREGIME_FX</TABELA>
			<NOME>ORIGEMEVENTO</NOME>
			<LEGENDAFORMULARIO>Origem do evento</LEGENDAFORMULARIO>
			<LEGENDAGRADE>Origem do evento</LEGENDAGRADE>
			<ORDEM>105</ORDEM>
			<DICA>Origem do evento da faixa</DICA>
			<PAGINA/>
			<CODIGOINTERNO/>
			<SISTEMA>N</SISTEMA>
			<OPCIONAL>N</OPCIONAL>
			<INVISIVEL>N</INVISIVEL>
			<SOLEITURA>S</SOLEITURA>
			<NOVALINHA>S</NOVALINHA>
			<MOSTRARGRID>S</MOSTRARGRID>
			<ALCLIENTE>N</ALCLIENTE>
			<CLASSE>6</CLASSE>
			<HERDARPERMISSAO/>
			<LARGURA/>
			<MASCARA/>
			<DECIMAIS/>
			<LARGURAFORMULARIO>40</LARGURAFORMULARIO>
			<MAIUSCULAS>N</MAIUSCULAS>
			<ASSUMIR/>
			<ASSUMIRINTEIRO/>
			<ASSUMIRREAL/>
			<ASSUMIRLOGICO/>
			<ASSUMIRDATA/>
			<MINIMO/>
			<MAXIMO/>
			<CAMPOMESTRE>SAM_PRECOGERALREGIME_FX|EVENTOINICIAL</CAMPOMESTRE>
			<CAMPOMESTREORIGINAL/>
			<ANCESTRAL/>
			<PESQUISAR>SAM_TGE</PESQUISAR>
			<RESULTADO>SAM_TGE|ORIGEMEVENTO</RESULTADO>
			<TEXTO/>
			<FLAGS>64</FLAGS>
			<FLAGS1>65544</FLAGS1>
			<FLAGS2>0</FLAGS2>
			<CLIDEF>N</CLIDEF>
			<Z_GRUPO/>
			<OBSERVACOES/>
			<PROPRIEDADE/>
			<HASH>E183233EDFB4E8E366D39BE6F9E5E6D8</HASH>
		</ORIGEMEVENTO>
		<PERCENTUALPGTOCUSTO>
			<TABELA>SAM_PRECOGERALREGIME_FX</TABELA>
			<NOME>PERCENTUALPGTOCUSTO</NOME>
			<LEGENDAFORMULARIO>% Pagamento</LEGENDAFORMULARIO>
			<LEGENDAGRADE>% Pagamento custo</LEGENDAGRADE>
			<ORDEM>186</ORDEM>
			<DICA>Percentual de pagamento do custo operacional</DICA>
			<PAGINA/>
			<CODIGOINTERNO/>
			<SISTEMA>N</SISTEMA>
			<OPCIONAL>S</OPCIONAL>
			<INVISIVEL>N</INVISIVEL>
			<SOLEITURA>N</SOLEITURA>
			<NOVALINHA>N</NOVALINHA>
			<MOSTRARGRID>S</MOSTRARGRID>
			<ALCLIENTE>N</ALCLIENTE>
			<CLASSE>3</CLASSE>
			<HERDARPERMISSAO/>
			<LARGURA>5</LARGURA>
			<MASCARA/>
			<DECIMAIS>2</DECIMAIS>
			<LARGURAFORMULARIO/>
			<MAIUSCULAS>N</MAIUSCULAS>
			<ASSUMIR/>
			<ASSUMIRINTEIRO/>
			<ASSUMIRREAL>100</ASSUMIRREAL>
			<ASSUMIRLOGICO/>
			<ASSUMIRDATA/>
			<MINIMO/>
			<MAXIMO/>
			<CAMPOMESTRE/>
			<CAMPOMESTREORIGINAL/>
			<ANCESTRAL/>
			<PESQUISAR/>
			<RESULTADO/>
			<TEXTO/>
			<FLAGS>131072</FLAGS>
			<FLAGS1>8</FLAGS1>
			<FLAGS2>0</FLAGS2>
			<CLIDEF>N</CLIDEF>
			<Z_GRUPO/>
			<OBSERVACOES/>
			<PROPRIEDADE/>
			<HASH>6004723ABD4F97EFE4048764BE4DD922</HASH>
		</PERCENTUALPGTOCUSTO>
		<PERCENTUALPGTOFILME>
			<TABELA>SAM_PRECOGERALREGIME_FX</TABELA>
			<NOME>PERCENTUALPGTOFILME</NOME>
			<LEGENDAFORMULARIO>% pagamento</LEGENDAFORMULARIO>
			<LEGENDAGRADE>% pagamento filme</LEGENDAGRADE>
			<ORDEM>175</ORDEM>
			<DICA>Percentual de pagamento para o Filme</DICA>
			<PAGINA/>
			<CODIGOINTERNO/>
			<SISTEMA>N</SISTEMA>
			<OPCIONAL>S</OPCIONAL>
			<INVISIVEL>N</INVISIVEL>
			<SOLEITURA>N</SOLEITURA>
			<NOVALINHA>N</NOVALINHA>
			<MOSTRARGRID>S</MOSTRARGRID>
			<ALCLIENTE>N</ALCLIENTE>
			<CLASSE>3</CLASSE>
			<HERDARPERMISSAO/>
			<LARGURA>5</LARGURA>
			<MASCARA/>
			<DECIMAIS>2</DECIMAIS>
			<LARGURAFORMULARIO/>
			<MAIUSCULAS>N</MAIUSCULAS>
			<ASSUMIR/>
			<ASSUMIRINTEIRO/>
			<ASSUMIRREAL>100</ASSUMIRREAL>
			<ASSUMIRLOGICO>N</ASSUMIRLOGICO>
			<ASSUMIRDATA/>
			<MINIMO/>
			<MAXIMO/>
			<CAMPOMESTRE/>
			<CAMPOMESTREORIGINAL/>
			<ANCESTRAL/>
			<PESQUISAR/>
			<RESULTADO/>
			<TEXTO/>
			<FLAGS>131072</FLAGS>
			<FLAGS1>8</FLAGS1>
			<FLAGS2>0</FLAGS2>
			<CLIDEF>N</CLIDEF>
			<Z_GRUPO/>
			<OBSERVACOES/>
			<PROPRIEDADE/>
			<HASH>D61105B457E30CB12D95AEB47D0C9FCE</HASH>
		</PERCENTUALPGTOFILME>
		<PERCENTUALPGTOUS>
			<TABELA>SAM_PRECOGERALREGIME_FX</TABELA>
			<NOME>PERCENTUALPGTOUS</NOME>
			<LEGENDAFORMULARIO>% pagamento</LEGENDAFORMULARIO>
			<LEGENDAGRADE>% pagamento US</LEGENDAGRADE>
			<ORDEM>165</ORDEM>
			<DICA>Percentual de pagamento para a US de honorários</DICA>
			<PAGINA/>
			<CODIGOINTERNO/>
			<SISTEMA>N</SISTEMA>
			<OPCIONAL>N</OPCIONAL>
			<INVISIVEL>N</INVISIVEL>
			<SOLEITURA>N</SOLEITURA>
			<NOVALINHA>N</NOVALINHA>
			<MOSTRARGRID>S</MOSTRARGRID>
			<ALCLIENTE>N</ALCLIENTE>
			<CLASSE>3</CLASSE>
			<HERDARPERMISSAO/>
			<LARGURA>5</LARGURA>
			<MASCARA/>
			<DECIMAIS>2</DECIMAIS>
			<LARGURAFORMULARIO/>
			<MAIUSCULAS>N</MAIUSCULAS>
			<ASSUMIR/>
			<ASSUMIRINTEIRO/>
			<ASSUMIRREAL>100</ASSUMIRREAL>
			<ASSUMIRLOGICO>N</ASSUMIRLOGICO>
			<ASSUMIRDATA/>
			<MINIMO/>
			<MAXIMO/>
			<CAMPOMESTRE/>
			<CAMPOMESTREORIGINAL/>
			<ANCESTRAL/>
			<PESQUISAR/>
			<RESULTADO/>
			<TEXTO/>
			<FLAGS>131072</FLAGS>
			<FLAGS1>8</FLAGS1>
			<FLAGS2>0</FLAGS2>
			<CLIDEF>N</CLIDEF>
			<Z_GRUPO/>
			<OBSERVACOES/>
			<PROPRIEDADE/>
			<HASH>54D625BC44F8710A27254B26761C3411</HASH>
		</PERCENTUALPGTOUS>
		<REGIMEATENDIMENTO>
			<TABELA>SAM_PRECOGERALREGIME_FX</TABELA>
			<NOME>REGIMEATENDIMENTO</NOME>
			<LEGENDAFORMULARIO>Regime de atendimento</LEGENDAFORMULARIO>
			<LEGENDAGRADE>Reg Atend</LEGENDAGRADE>
			<ORDEM>100</ORDEM>
			<DICA>Código do Regime de Atendimento</DICA>
			<PAGINA/>
			<CODIGOINTERNO/>
			<SISTEMA>N</SISTEMA>
			<OPCIONAL>N</OPCIONAL>
			<INVISIVEL>S</INVISIVEL>
			<SOLEITURA>N</SOLEITURA>
			<NOVALINHA>N</NOVALINHA>
			<MOSTRARGRID>S</MOSTRARGRID>
			<ALCLIENTE>N</ALCLIENTE>
			<CLASSE>6</CLASSE>
			<HERDARPERMISSAO/>
			<LARGURA/>
			<MASCARA/>
			<DECIMAIS/>
			<LARGURAFORMULARIO/>
			<MAIUSCULAS>N</MAIUSCULAS>
			<ASSUMIR/>
			<ASSUMIRINTEIRO/>
			<ASSUMIRREAL/>
			<ASSUMIRLOGICO>N</ASSUMIRLOGICO>
			<ASSUMIRDATA/>
			<MINIMO/>
			<MAXIMO/>
			<CAMPOMESTRE/>
			<CAMPOMESTREORIGINAL/>
			<ANCESTRAL/>
			<PESQUISAR>SAM_REGIMEATENDIMENTO</PESQUISAR>
			<RESULTADO>SAM_REGIMEATENDIMENTO|DESCRICAO</RESULTADO>
			<TEXTO/>
			<FLAGS>4096</FLAGS>
			<FLAGS1>264</FLAGS1>
			<FLAGS2>0</FLAGS2>
			<CLIDEF>N</CLIDEF>
			<Z_GRUPO/>
			<OBSERVACOES/>
			<PROPRIEDADE/>
			<HASH>25B9299125974E8665D00699954DADDD</HASH>
		</REGIMEATENDIMENTO>
		<TABELACUSTOOPERAC>
			<TABELA>SAM_PRECOGERALREGIME_FX</TABELA>
			<NOME>TABELACUSTOOPERAC</NOME>
			<LEGENDAFORMULARIO>Tabela de custo operacional</LEGENDAFORMULARIO>
			<LEGENDAGRADE>Tabela de custo operacional</LEGENDAGRADE>
			<ORDEM>182</ORDEM>
			<DICA>Informe a Tabela de custo operacional</DICA>
			<PAGINA/>
			<CODIGOINTERNO/>
			<SISTEMA>N</SISTEMA>
			<OPCIONAL>S</OPCIONAL>
			<INVISIVEL>N</INVISIVEL>
			<SOLEITURA>N</SOLEITURA>
			<NOVALINHA>S</NOVALINHA>
			<MOSTRARGRID>S</MOSTRARGRID>
			<ALCLIENTE>N</ALCLIENTE>
			<CLASSE>6</CLASSE>
			<HERDARPERMISSAO/>
			<LARGURA/>
			<MASCARA/>
			<DECIMAIS/>
			<LARGURAFORMULARIO/>
			<MAIUSCULAS>N</MAIUSCULAS>
			<ASSUMIR/>
			<ASSUMIRINTEIRO/>
			<ASSUMIRREAL/>
			<ASSUMIRLOGICO/>
			<ASSUMIRDATA/>
			<MINIMO/>
			<MAXIMO/>
			<CAMPOMESTRE/>
			<CAMPOMESTREORIGINAL/>
			<ANCESTRAL/>
			<PESQUISAR>SAM_TABCUSTOOPERAC</PESQUISAR>
			<RESULTADO>SAM_TABCUSTOOPERAC|DESCRICAO</RESULTADO>
			<TEXTO/>
			<FLAGS>4096</FLAGS>
			<FLAGS1>264</FLAGS1>
			<FLAGS2>0</FLAGS2>
			<CLIDEF>N</CLIDEF>
			<Z_GRUPO/>
			<OBSERVACOES/>
			<PROPRIEDADE/>
			<HASH>D7BFC8EE039ED069C519ED4E136AE950</HASH>
		</TABELACUSTOOPERAC>
		<TABELAFILME>
			<TABELA>SAM_PRECOGERALREGIME_FX</TABELA>
			<NOME>TABELAFILME</NOME>
			<LEGENDAFORMULARIO>Tabela de filme</LEGENDAFORMULARIO>
			<LEGENDAGRADE>Tabela de filme</LEGENDAGRADE>
			<ORDEM>170</ORDEM>
			<DICA>Informe o Código da Tabela de Filme</DICA>
			<PAGINA/>
			<CODIGOINTERNO/>
			<SISTEMA>N</SISTEMA>
			<OPCIONAL>S</OPCIONAL>
			<INVISIVEL>N</INVISIVEL>
			<SOLEITURA>N</SOLEITURA>
			<NOVALINHA>S</NOVALINHA>
			<MOSTRARGRID>S</MOSTRARGRID>
			<ALCLIENTE>N</ALCLIENTE>
			<CLASSE>6</CLASSE>
			<HERDARPERMISSAO/>
			<LARGURA>10</LARGURA>
			<MASCARA/>
			<DECIMAIS/>
			<LARGURAFORMULARIO/>
			<MAIUSCULAS>N</MAIUSCULAS>
			<ASSUMIR/>
			<ASSUMIRINTEIRO/>
			<ASSUMIRREAL/>
			<ASSUMIRLOGICO>N</ASSUMIRLOGICO>
			<ASSUMIRDATA/>
			<MINIMO/>
			<MAXIMO/>
			<CAMPOMESTRE/>
			<CAMPOMESTREORIGINAL/>
			<ANCESTRAL/>
			<PESQUISAR>SAM_TABFILME</PESQUISAR>
			<RESULTADO>SAM_TABFILME|DESCRICAO</RESULTADO>
			<TEXTO/>
			<FLAGS>4096</FLAGS>
			<FLAGS1>264</FLAGS1>
			<FLAGS2>0</FLAGS2>
			<CLIDEF>N</CLIDEF>
			<Z_GRUPO/>
			<OBSERVACOES/>
			<PROPRIEDADE/>
			<HASH>7D1510B2EBB734238EF2426DA9B92194</HASH>
		</TABELAFILME>
		<TABELAPRECO>
			<TABELA>SAM_PRECOGERALREGIME_FX</TABELA>
			<NOME>TABELAPRECO</NOME>
			<LEGENDAFORMULARIO>Tabela genérica</LEGENDAFORMULARIO>
			<LEGENDAGRADE>Tabela genérica</LEGENDAGRADE>
			<ORDEM>096</ORDEM>
			<DICA>Tabela genérica para o preço da faixa</DICA>
			<PAGINA/>
			<CODIGOINTERNO/>
			<SISTEMA>N</SISTEMA>
			<OPCIONAL>S</OPCIONAL>
			<INVISIVEL>N</INVISIVEL>
			<SOLEITURA>N</SOLEITURA>
			<NOVALINHA>S</NOVALINHA>
			<MOSTRARGRID>S</MOSTRARGRID>
			<ALCLIENTE>N</ALCLIENTE>
			<CLASSE>6</CLASSE>
			<HERDARPERMISSAO/>
			<LARGURA/>
			<MASCARA/>
			<DECIMAIS/>
			<LARGURAFORMULARIO/>
			<MAIUSCULAS>N</MAIUSCULAS>
			<ASSUMIR/>
			<ASSUMIRINTEIRO/>
			<ASSUMIRREAL/>
			<ASSUMIRLOGICO>N</ASSUMIRLOGICO>
			<ASSUMIRDATA/>
			<MINIMO/>
			<MAXIMO/>
			<CAMPOMESTRE/>
			<CAMPOMESTREORIGINAL/>
			<ANCESTRAL/>
			<PESQUISAR>SAM_PRECOGENERICO</PESQUISAR>
			<RESULTADO>SAM_PRECOGENERICO|DESCRICAO</RESULTADO>
			<TEXTO/>
			<FLAGS>4096</FLAGS>
			<FLAGS1>264</FLAGS1>
			<FLAGS2>0</FLAGS2>
			<CLIDEF>N</CLIDEF>
			<Z_GRUPO/>
			<OBSERVACOES/>
			<PROPRIEDADE/>
			<HASH>F4F6ECD231880D278940290CF6683BAC</HASH>
		</TABELAPRECO>
		<TABELAUS>
			<TABELA>SAM_PRECOGERALREGIME_FX</TABELA>
			<NOME>TABELAUS</NOME>
			<LEGENDAFORMULARIO>Tabela US</LEGENDAFORMULARIO>
			<LEGENDAGRADE>Tabela US</LEGENDAGRADE>
			<ORDEM>160</ORDEM>
			<DICA>Informe a tabela a ser utilizada para a US de honorários</DICA>
			<PAGINA/>
			<CODIGOINTERNO/>
			<SISTEMA>N</SISTEMA>
			<OPCIONAL>S</OPCIONAL>
			<INVISIVEL>N</INVISIVEL>
			<SOLEITURA>N</SOLEITURA>
			<NOVALINHA>S</NOVALINHA>
			<MOSTRARGRID>S</MOSTRARGRID>
			<ALCLIENTE>N</ALCLIENTE>
			<CLASSE>6</CLASSE>
			<HERDARPERMISSAO/>
			<LARGURA/>
			<MASCARA/>
			<DECIMAIS/>
			<LARGURAFORMULARIO/>
			<MAIUSCULAS>N</MAIUSCULAS>
			<ASSUMIR/>
			<ASSUMIRINTEIRO/>
			<ASSUMIRREAL/>
			<ASSUMIRLOGICO>N</ASSUMIRLOGICO>
			<ASSUMIRDATA/>
			<MINIMO/>
			<MAXIMO/>
			<CAMPOMESTRE/>
			<CAMPOMESTREORIGINAL/>
			<ANCESTRAL/>
			<PESQUISAR>SAM_TABUS</PESQUISAR>
			<RESULTADO>SAM_TABUS|DESCRICAO</RESULTADO>
			<TEXTO/>
			<FLAGS>4096</FLAGS>
			<FLAGS1>264</FLAGS1>
			<FLAGS2>0</FLAGS2>
			<CLIDEF>N</CLIDEF>
			<Z_GRUPO/>
			<OBSERVACOES/>
			<PROPRIEDADE/>
			<HASH>AFE5AC89914151ACAC612117417A545E</HASH>
		</TABELAUS>
	</Campos>
	<Indices>
		<ESTRUTURAINICIAL_virgula__t_ESTRUTURAFINAL>
			<Z_GRUPO/>
			<UNICO>N</UNICO>
			<CAMPOS>ESTRUTURAINICIAL, ESTRUTURAFINAL</CAMPOS>
			<CLIDEF>N</CLIDEF>
			<FLAGS>0</FLAGS>
			<AUTOMATICO>N</AUTOMATICO>
			<EXCLUIDO>N</EXCLUIDO>
			<FUNCAO/>
			<DEFINICAOMANUAL/>
			<HASH>0432C1A76CA59AF2ACC58A92117178A0</HASH>
		</ESTRUTURAINICIAL_virgula__t_ESTRUTURAFINAL>
	</Indices>
</Tabela>
