<?xml version="1.0"?>
<Tabela>
	<Configuracoes>
		<HASH>CC2C47239BC999E70A8DBDEE9BDDCC93</HASH>
		<NOME>TV_FILTRO0057</NOME>
		<APELIDO/>
		<LEGENDA>TV_FILTRO0057</LEGENDA>
		<LOCAL>V</LOCAL>
		<TIPO>N</TIPO>
		<GENERICA>N</GENERICA>
		<DESENVOLVIMENTO>N</DESENVOLVIMENTO>
		<SOLEITURA>N</SOLEITURA>
		<PROTEGERREGISTRO>N</PROTEGERREGISTRO>
		<POREMPRESA>N</POREMPRESA>
		<PORPERIODO>N</PORPERIODO>
		<PORFILIAL>N</PORFILIAL>
		<AGENDA>N</AGENDA>
		<CODIGOINTERNO>0</CODIGOINTERNO>
		<CLIDEF>N</CLIDEF>
		<FLAGS>0</FLAGS>
		<CHAVEDB2EEE/>
		<TOPICOAJUDA>Site: 9907</TOPICOAJUDA>
		<TSPACE/>
		<TSPACELONG/>
		<TSPACEINDEX/>
		<Z_GRUPO/>
		<OBSERVACOES/>
		<TABELAFISICA/>
		<TIPOPARTICIONAMENTO>1</TIPOPARTICIONAMENTO>
		<ORIGEM>2</ORIGEM>
		<COMANDO/>
		<Z_EXCLUIDO/>
		<ENTIDADE/>
	</Configuracoes>
	<Campos>
		<CONFIGURACAO>
			<TABELA>TV_FILTRO0057</TABELA>
			<NOME>CONFIGURACAO</NOME>
			<LEGENDAFORMULARIO>Configuração</LEGENDAFORMULARIO>
			<LEGENDAGRADE>Configuração</LEGENDAGRADE>
			<ORDEM>110</ORDEM>
			<DICA/>
			<PAGINA/>
			<CODIGOINTERNO/>
			<SISTEMA>N</SISTEMA>
			<OPCIONAL>S</OPCIONAL>
			<INVISIVEL>N</INVISIVEL>
			<SOLEITURA>S</SOLEITURA>
			<NOVALINHA>N</NOVALINHA>
			<MOSTRARGRID>S</MOSTRARGRID>
			<ALCLIENTE>N</ALCLIENTE>
			<CLASSE>6</CLASSE>
			<HERDARPERMISSAO/>
			<LARGURA/>
			<MASCARA/>
			<DECIMAIS/>
			<LARGURAFORMULARIO/>
			<MAIUSCULAS>N</MAIUSCULAS>
			<ASSUMIR/>
			<ASSUMIRINTEIRO/>
			<ASSUMIRREAL/>
			<ASSUMIRLOGICO/>
			<ASSUMIRDATA/>
			<MINIMO/>
			<MAXIMO/>
			<CAMPOMESTRE/>
			<CAMPOMESTREORIGINAL/>
			<ANCESTRAL>TV_FILTRO0057|ROTINAEMISSAO</ANCESTRAL>
			<PESQUISAR>SAM_LIVROCONFIG</PESQUISAR>
			<RESULTADO>SAM_LIVROCONFIG|CODIGO</RESULTADO>
			<TEXTO/>
			<FLAGS>4096</FLAGS>
			<FLAGS1>40</FLAGS1>
			<FLAGS2>0</FLAGS2>
			<CLIDEF>N</CLIDEF>
			<Z_GRUPO/>
			<OBSERVACOES/>
			<PROPRIEDADE/>
			<HASH>F39CF650204E24C9DBB88E36D2A54382</HASH>
		</CONFIGURACAO>
		<CONSIDERARCONTIDAS>
			<TABELA>TV_FILTRO0057</TABELA>
			<NOME>CONSIDERARCONTIDAS</NOME>
			<LEGENDAFORMULARIO>Considerar redes contidas</LEGENDAFORMULARIO>
			<LEGENDAGRADE>Considerar redes contidas</LEGENDAGRADE>
			<ORDEM>080</ORDEM>
			<DICA/>
			<PAGINA/>
			<CODIGOINTERNO/>
			<SISTEMA>N</SISTEMA>
			<OPCIONAL>N</OPCIONAL>
			<INVISIVEL>N</INVISIVEL>
			<SOLEITURA>S</SOLEITURA>
			<NOVALINHA>S</NOVALINHA>
			<MOSTRARGRID>S</MOSTRARGRID>
			<ALCLIENTE>N</ALCLIENTE>
			<CLASSE>4</CLASSE>
			<HERDARPERMISSAO/>
			<LARGURA/>
			<MASCARA/>
			<DECIMAIS/>
			<LARGURAFORMULARIO/>
			<MAIUSCULAS>N</MAIUSCULAS>
			<ASSUMIR/>
			<ASSUMIRINTEIRO/>
			<ASSUMIRREAL/>
			<ASSUMIRLOGICO>N</ASSUMIRLOGICO>
			<ASSUMIRDATA/>
			<MINIMO/>
			<MAXIMO/>
			<CAMPOMESTRE/>
			<CAMPOMESTREORIGINAL/>
			<ANCESTRAL>TV_FILTRO0057|ROTINAEMISSAO</ANCESTRAL>
			<PESQUISAR/>
			<RESULTADO/>
			<TEXTO/>
			<FLAGS>0</FLAGS>
			<FLAGS1>8</FLAGS1>
			<FLAGS2>0</FLAGS2>
			<CLIDEF>N</CLIDEF>
			<Z_GRUPO/>
			<OBSERVACOES/>
			<PROPRIEDADE/>
			<HASH>4D4C68180E6F77EC51296052E1CB93C9</HASH>
		</CONSIDERARCONTIDAS>
		<CONTROLE>
			<TABELA>TV_FILTRO0057</TABELA>
			<NOME>CONTROLE</NOME>
			<LEGENDAFORMULARIO>Controle</LEGENDAFORMULARIO>
			<LEGENDAGRADE>Controle</LEGENDAGRADE>
			<ORDEM>120</ORDEM>
			<DICA/>
			<PAGINA/>
			<CODIGOINTERNO/>
			<SISTEMA>N</SISTEMA>
			<OPCIONAL>N</OPCIONAL>
			<INVISIVEL>N</INVISIVEL>
			<SOLEITURA>N</SOLEITURA>
			<NOVALINHA>N</NOVALINHA>
			<MOSTRARGRID>S</MOSTRARGRID>
			<ALCLIENTE>N</ALCLIENTE>
			<CLASSE>15</CLASSE>
			<HERDARPERMISSAO/>
			<LARGURA/>
			<MASCARA/>
			<DECIMAIS/>
			<LARGURAFORMULARIO/>
			<MAIUSCULAS>N</MAIUSCULAS>
			<ASSUMIR/>
			<ASSUMIRINTEIRO/>
			<ASSUMIRREAL/>
			<ASSUMIRLOGICO/>
			<ASSUMIRDATA/>
			<MINIMO/>
			<MAXIMO/>
			<CAMPOMESTRE/>
			<CAMPOMESTREORIGINAL/>
			<ANCESTRAL/>
			<PESQUISAR/>
			<RESULTADO/>
			<TEXTO>1#DATAEMISSAO|S|RESPONSAVEL|S|</TEXTO>
			<FLAGS>0</FLAGS>
			<FLAGS1>8</FLAGS1>
			<FLAGS2>0</FLAGS2>
			<CLIDEF>N</CLIDEF>
			<Z_GRUPO/>
			<OBSERVACOES/>
			<PROPRIEDADE/>
			<HASH>107BD537530E6261977E5F638F51574F</HASH>
		</CONTROLE>
		<DATAEMISSAO>
			<TABELA>TV_FILTRO0057</TABELA>
			<NOME>DATAEMISSAO</NOME>
			<LEGENDAFORMULARIO>Data da emissão</LEGENDAFORMULARIO>
			<LEGENDAGRADE>Data da emissão</LEGENDAGRADE>
			<ORDEM>130</ORDEM>
			<DICA/>
			<PAGINA/>
			<CODIGOINTERNO/>
			<SISTEMA>N</SISTEMA>
			<OPCIONAL>S</OPCIONAL>
			<INVISIVEL>N</INVISIVEL>
			<SOLEITURA>S</SOLEITURA>
			<NOVALINHA>N</NOVALINHA>
			<MOSTRARGRID>S</MOSTRARGRID>
			<ALCLIENTE>N</ALCLIENTE>
			<CLASSE>5</CLASSE>
			<HERDARPERMISSAO/>
			<LARGURA/>
			<MASCARA/>
			<DECIMAIS/>
			<LARGURAFORMULARIO/>
			<MAIUSCULAS>N</MAIUSCULAS>
			<ASSUMIR/>
			<ASSUMIRINTEIRO/>
			<ASSUMIRREAL/>
			<ASSUMIRLOGICO/>
			<ASSUMIRDATA/>
			<MINIMO/>
			<MAXIMO/>
			<CAMPOMESTRE/>
			<CAMPOMESTREORIGINAL/>
			<ANCESTRAL>TV_FILTRO0057|ROTINAEMISSAO</ANCESTRAL>
			<PESQUISAR/>
			<RESULTADO/>
			<TEXTO/>
			<FLAGS>128</FLAGS>
			<FLAGS1>8</FLAGS1>
			<FLAGS2>0</FLAGS2>
			<CLIDEF>N</CLIDEF>
			<Z_GRUPO/>
			<OBSERVACOES/>
			<PROPRIEDADE/>
			<HASH>9E73C5F0FADBB129C2D515A1AB5C8C05</HASH>
		</DATAEMISSAO>
		<LIVRO>
			<TABELA>TV_FILTRO0057</TABELA>
			<NOME>LIVRO</NOME>
			<LEGENDAFORMULARIO>Livro</LEGENDAFORMULARIO>
			<LEGENDAGRADE>Livro</LEGENDAGRADE>
			<ORDEM>090</ORDEM>
			<DICA/>
			<PAGINA/>
			<CODIGOINTERNO/>
			<SISTEMA>N</SISTEMA>
			<OPCIONAL>S</OPCIONAL>
			<INVISIVEL>N</INVISIVEL>
			<SOLEITURA>S</SOLEITURA>
			<NOVALINHA>S</NOVALINHA>
			<MOSTRARGRID>S</MOSTRARGRID>
			<ALCLIENTE>N</ALCLIENTE>
			<CLASSE>6</CLASSE>
			<HERDARPERMISSAO/>
			<LARGURA/>
			<MASCARA/>
			<DECIMAIS/>
			<LARGURAFORMULARIO/>
			<MAIUSCULAS>N</MAIUSCULAS>
			<ASSUMIR/>
			<ASSUMIRINTEIRO/>
			<ASSUMIRREAL/>
			<ASSUMIRLOGICO/>
			<ASSUMIRDATA/>
			<MINIMO/>
			<MAXIMO/>
			<CAMPOMESTRE/>
			<CAMPOMESTREORIGINAL/>
			<ANCESTRAL>TV_FILTRO0057|ROTINAEMISSAO</ANCESTRAL>
			<PESQUISAR>SAM_LIVRO</PESQUISAR>
			<RESULTADO>SAM_LIVRO|EDICAO</RESULTADO>
			<TEXTO/>
			<FLAGS>4096</FLAGS>
			<FLAGS1>40</FLAGS1>
			<FLAGS2>0</FLAGS2>
			<CLIDEF>N</CLIDEF>
			<Z_GRUPO/>
			<OBSERVACOES/>
			<PROPRIEDADE/>
			<HASH>AD625BC4DD2AD668D94C9E4689055D57</HASH>
		</LIVRO>
		<LIVROENCARTE>
			<TABELA>TV_FILTRO0057</TABELA>
			<NOME>LIVROENCARTE</NOME>
			<LEGENDAFORMULARIO>Encarte</LEGENDAFORMULARIO>
			<LEGENDAGRADE>Encarte</LEGENDAGRADE>
			<ORDEM>100</ORDEM>
			<DICA/>
			<PAGINA/>
			<CODIGOINTERNO/>
			<SISTEMA>N</SISTEMA>
			<OPCIONAL>S</OPCIONAL>
			<INVISIVEL>N</INVISIVEL>
			<SOLEITURA>S</SOLEITURA>
			<NOVALINHA>N</NOVALINHA>
			<MOSTRARGRID>S</MOSTRARGRID>
			<ALCLIENTE>N</ALCLIENTE>
			<CLASSE>6</CLASSE>
			<HERDARPERMISSAO/>
			<LARGURA/>
			<MASCARA/>
			<DECIMAIS/>
			<LARGURAFORMULARIO/>
			<MAIUSCULAS>N</MAIUSCULAS>
			<ASSUMIR/>
			<ASSUMIRINTEIRO/>
			<ASSUMIRREAL/>
			<ASSUMIRLOGICO/>
			<ASSUMIRDATA/>
			<MINIMO/>
			<MAXIMO/>
			<CAMPOMESTRE/>
			<CAMPOMESTREORIGINAL/>
			<ANCESTRAL>TV_FILTRO0057|ROTINAEMISSAO</ANCESTRAL>
			<PESQUISAR>SAM_LIVROENCARTE</PESQUISAR>
			<RESULTADO>SAM_LIVROENCARTE|LIVRONUMERO</RESULTADO>
			<TEXTO/>
			<FLAGS>4096</FLAGS>
			<FLAGS1>40</FLAGS1>
			<FLAGS2>0</FLAGS2>
			<CLIDEF>N</CLIDEF>
			<Z_GRUPO/>
			<OBSERVACOES/>
			<PROPRIEDADE/>
			<HASH>C0C741B36639EABAD56A4F16140EDD05</HASH>
		</LIVROENCARTE>
		<RESPONSAVEL>
			<TABELA>TV_FILTRO0057</TABELA>
			<NOME>RESPONSAVEL</NOME>
			<LEGENDAFORMULARIO>Responsável</LEGENDAFORMULARIO>
			<LEGENDAGRADE>Responsável</LEGENDAGRADE>
			<ORDEM>140</ORDEM>
			<DICA/>
			<PAGINA/>
			<CODIGOINTERNO/>
			<SISTEMA>N</SISTEMA>
			<OPCIONAL>S</OPCIONAL>
			<INVISIVEL>N</INVISIVEL>
			<SOLEITURA>S</SOLEITURA>
			<NOVALINHA>N</NOVALINHA>
			<MOSTRARGRID>S</MOSTRARGRID>
			<ALCLIENTE>N</ALCLIENTE>
			<CLASSE>6</CLASSE>
			<HERDARPERMISSAO/>
			<LARGURA/>
			<MASCARA/>
			<DECIMAIS/>
			<LARGURAFORMULARIO/>
			<MAIUSCULAS>N</MAIUSCULAS>
			<ASSUMIR/>
			<ASSUMIRINTEIRO/>
			<ASSUMIRREAL/>
			<ASSUMIRLOGICO/>
			<ASSUMIRDATA/>
			<MINIMO/>
			<MAXIMO/>
			<CAMPOMESTRE/>
			<CAMPOMESTREORIGINAL/>
			<ANCESTRAL>TV_FILTRO0057|ROTINAEMISSAO</ANCESTRAL>
			<PESQUISAR>Z_GRUPOUSUARIOS</PESQUISAR>
			<RESULTADO>Z_GRUPOUSUARIOS|NOME</RESULTADO>
			<TEXTO/>
			<FLAGS>0</FLAGS>
			<FLAGS1>40</FLAGS1>
			<FLAGS2>0</FLAGS2>
			<CLIDEF>N</CLIDEF>
			<Z_GRUPO/>
			<OBSERVACOES/>
			<PROPRIEDADE/>
			<HASH>4DE97BB9C280488761150E33647AE6B9</HASH>
		</RESPONSAVEL>
		<ROTINAEMISSAO>
			<TABELA>TV_FILTRO0057</TABELA>
			<NOME>ROTINAEMISSAO</NOME>
			<LEGENDAFORMULARIO>Rotina de Emissão</LEGENDAFORMULARIO>
			<LEGENDAGRADE>Rotina de Emissão</LEGENDAGRADE>
			<ORDEM>050</ORDEM>
			<DICA/>
			<PAGINA/>
			<CODIGOINTERNO/>
			<SISTEMA>N</SISTEMA>
			<OPCIONAL>N</OPCIONAL>
			<INVISIVEL>N</INVISIVEL>
			<SOLEITURA>N</SOLEITURA>
			<NOVALINHA>N</NOVALINHA>
			<MOSTRARGRID>S</MOSTRARGRID>
			<ALCLIENTE>N</ALCLIENTE>
			<CLASSE>6</CLASSE>
			<HERDARPERMISSAO/>
			<LARGURA/>
			<MASCARA/>
			<DECIMAIS/>
			<LARGURAFORMULARIO/>
			<MAIUSCULAS>N</MAIUSCULAS>
			<ASSUMIR/>
			<ASSUMIRINTEIRO/>
			<ASSUMIRREAL/>
			<ASSUMIRLOGICO/>
			<ASSUMIRDATA/>
			<MINIMO/>
			<MAXIMO/>
			<CAMPOMESTRE/>
			<CAMPOMESTREORIGINAL/>
			<ANCESTRAL/>
			<PESQUISAR>SAM_LIVRO_ROTINAEMISSAO</PESQUISAR>
			<RESULTADO>SAM_LIVRO_ROTINAEMISSAO|ROTINA</RESULTADO>
			<TEXTO>TIPORELATORIO = 'C'</TEXTO>
			<FLAGS>4096</FLAGS>
			<FLAGS1>40</FLAGS1>
			<FLAGS2>0</FLAGS2>
			<CLIDEF>N</CLIDEF>
			<Z_GRUPO/>
			<OBSERVACOES/>
			<PROPRIEDADE/>
			<HASH>31FB5EBFA50D25155B5427A878FC9792</HASH>
		</ROTINAEMISSAO>
		<TIPOEMISSAO>
			<TABELA>TV_FILTRO0057</TABELA>
			<NOME>TIPOEMISSAO</NOME>
			<LEGENDAFORMULARIO>Tipo Emissão</LEGENDAFORMULARIO>
			<LEGENDAGRADE>Tipo Emissão</LEGENDAGRADE>
			<ORDEM>070</ORDEM>
			<DICA/>
			<PAGINA/>
			<CODIGOINTERNO/>
			<SISTEMA>N</SISTEMA>
			<OPCIONAL>N</OPCIONAL>
			<INVISIVEL>N</INVISIVEL>
			<SOLEITURA>S</SOLEITURA>
			<NOVALINHA>N</NOVALINHA>
			<MOSTRARGRID>S</MOSTRARGRID>
			<ALCLIENTE>N</ALCLIENTE>
			<CLASSE>18</CLASSE>
			<HERDARPERMISSAO/>
			<LARGURA/>
			<MASCARA/>
			<DECIMAIS/>
			<LARGURAFORMULARIO/>
			<MAIUSCULAS>N</MAIUSCULAS>
			<ASSUMIR>C</ASSUMIR>
			<ASSUMIRINTEIRO/>
			<ASSUMIRREAL/>
			<ASSUMIRLOGICO/>
			<ASSUMIRDATA/>
			<MINIMO/>
			<MAXIMO/>
			<CAMPOMESTRE/>
			<CAMPOMESTREORIGINAL/>
			<ANCESTRAL>TV_FILTRO0057|ROTINAEMISSAO</ANCESTRAL>
			<PESQUISAR/>
			<RESULTADO/>
			<TEXTO>1#Completa|C|S|Encarte(incremental)|E|S|</TEXTO>
			<FLAGS>0</FLAGS>
			<FLAGS1>8</FLAGS1>
			<FLAGS2>1</FLAGS2>
			<CLIDEF>N</CLIDEF>
			<Z_GRUPO/>
			<OBSERVACOES/>
			<PROPRIEDADE/>
			<HASH>4303127F0AC3ECA52EFF853D89581500</HASH>
		</TIPOEMISSAO>
		<TIPORELATORIO>
			<TABELA>TV_FILTRO0057</TABELA>
			<NOME>TIPORELATORIO</NOME>
			<LEGENDAFORMULARIO>Tipo do Relatorio</LEGENDAFORMULARIO>
			<LEGENDAGRADE>Tipo do Relatorio</LEGENDAGRADE>
			<ORDEM>060</ORDEM>
			<DICA/>
			<PAGINA/>
			<CODIGOINTERNO/>
			<SISTEMA>N</SISTEMA>
			<OPCIONAL>N</OPCIONAL>
			<INVISIVEL>N</INVISIVEL>
			<SOLEITURA>S</SOLEITURA>
			<NOVALINHA>S</NOVALINHA>
			<MOSTRARGRID>S</MOSTRARGRID>
			<ALCLIENTE>N</ALCLIENTE>
			<CLASSE>18</CLASSE>
			<HERDARPERMISSAO/>
			<LARGURA/>
			<MASCARA/>
			<DECIMAIS/>
			<LARGURAFORMULARIO/>
			<MAIUSCULAS>N</MAIUSCULAS>
			<ASSUMIR>C</ASSUMIR>
			<ASSUMIRINTEIRO/>
			<ASSUMIRREAL/>
			<ASSUMIRLOGICO/>
			<ASSUMIRDATA/>
			<MINIMO/>
			<MAXIMO/>
			<CAMPOMESTRE/>
			<CAMPOMESTREORIGINAL/>
			<ANCESTRAL>TV_FILTRO0057|ROTINAEMISSAO</ANCESTRAL>
			<PESQUISAR/>
			<RESULTADO/>
			<TEXTO>1#Completo     |C|S|Resumido    |R|S|</TEXTO>
			<FLAGS>0</FLAGS>
			<FLAGS1>8</FLAGS1>
			<FLAGS2>1</FLAGS2>
			<CLIDEF>N</CLIDEF>
			<Z_GRUPO/>
			<OBSERVACOES/>
			<PROPRIEDADE/>
			<HASH>686C7E95639D3F6614E940B1EB655CD0</HASH>
		</TIPORELATORIO>
	</Campos>
</Tabela>
