<?xml version="1.0"?>
<Tabela>
	<Configuracoes>
		<HASH>5A7371106FE8EAD4CA6A3B27714498F9</HASH>
		<NOME>TV_FORM0073</NOME>
		<APELIDO/>
		<LEGENDA>Geração dos Registros Auxiliares</LEGENDA>
		<LOCAL>V</LOCAL>
		<TIPO>N</TIPO>
		<GENERICA>N</GENERICA>
		<DESENVOLVIMENTO>N</DESENVOLVIMENTO>
		<SOLEITURA>N</SOLEITURA>
		<PROTEGERREGISTRO>N</PROTEGERREGISTRO>
		<POREMPRESA>N</POREMPRESA>
		<PORPERIODO>N</PORPERIODO>
		<PORFILIAL>N</PORFILIAL>
		<AGENDA>N</AGENDA>
		<CODIGOINTERNO>0</CODIGOINTERNO>
		<CLIDEF>N</CLIDEF>
		<FLAGS>0</FLAGS>
		<CHAVEDB2EEE/>
		<TOPICOAJUDA/>
		<TSPACE/>
		<TSPACELONG/>
		<TSPACEINDEX/>
		<Z_GRUPO/>
		<OBSERVACOES/>
		<TABELAFISICA/>
		<TIPOPARTICIONAMENTO>1</TIPOPARTICIONAMENTO>
		<ORIGEM>2</ORIGEM>
		<COMANDO/>
		<Z_EXCLUIDO/>
		<ENTIDADE>GeracaoCancelamentoRegistrosAuxiliares</ENTIDADE>
	</Configuracoes>
	<Campos>
		<CHECK01>
			<TABELA>TV_FORM0073</TABELA>
			<NOME>CHECK01</NOME>
			<LEGENDAFORMULARIO>1 - Contratos e contraprest. emitidas</LEGENDAFORMULARIO>
			<LEGENDAGRADE>1 - Contratos e contraprest. emitidas</LEGENDAGRADE>
			<ORDEM>050</ORDEM>
			<DICA>1 - Contratos e contraprest. emitidas</DICA>
			<PAGINA/>
			<CODIGOINTERNO/>
			<SISTEMA>N</SISTEMA>
			<OPCIONAL>N</OPCIONAL>
			<INVISIVEL>N</INVISIVEL>
			<SOLEITURA>S</SOLEITURA>
			<NOVALINHA>S</NOVALINHA>
			<MOSTRARGRID>S</MOSTRARGRID>
			<ALCLIENTE>N</ALCLIENTE>
			<CLASSE>4</CLASSE>
			<HERDARPERMISSAO/>
			<LARGURA/>
			<MASCARA/>
			<DECIMAIS/>
			<LARGURAFORMULARIO/>
			<MAIUSCULAS>N</MAIUSCULAS>
			<ASSUMIR/>
			<ASSUMIRINTEIRO/>
			<ASSUMIRREAL/>
			<ASSUMIRLOGICO>S</ASSUMIRLOGICO>
			<ASSUMIRDATA/>
			<MINIMO/>
			<MAXIMO/>
			<CAMPOMESTRE/>
			<CAMPOMESTREORIGINAL/>
			<ANCESTRAL/>
			<PESQUISAR/>
			<RESULTADO/>
			<TEXTO/>
			<FLAGS>0</FLAGS>
			<FLAGS1>8</FLAGS1>
			<FLAGS2>0</FLAGS2>
			<CLIDEF>N</CLIDEF>
			<Z_GRUPO/>
			<OBSERVACOES/>
			<PROPRIEDADE>ContratosEContraprestEmitidas</PROPRIEDADE>
			<HASH>E77900B635A1A73E3E78282DC7ADE00C</HASH>
		</CHECK01>
		<CHECK02>
			<TABELA>TV_FORM0073</TABELA>
			<NOME>CHECK02</NOME>
			<LEGENDAFORMULARIO>2 - Contraprestações rec., rest. e canc</LEGENDAFORMULARIO>
			<LEGENDAGRADE>2 - Contraprestações rec., rest. e canc</LEGENDAGRADE>
			<ORDEM>060</ORDEM>
			<DICA>2 - Contraprestações rec., rest. e canc</DICA>
			<PAGINA/>
			<CODIGOINTERNO/>
			<SISTEMA>N</SISTEMA>
			<OPCIONAL>N</OPCIONAL>
			<INVISIVEL>N</INVISIVEL>
			<SOLEITURA>S</SOLEITURA>
			<NOVALINHA>S</NOVALINHA>
			<MOSTRARGRID>S</MOSTRARGRID>
			<ALCLIENTE>N</ALCLIENTE>
			<CLASSE>4</CLASSE>
			<HERDARPERMISSAO/>
			<LARGURA/>
			<MASCARA/>
			<DECIMAIS/>
			<LARGURAFORMULARIO/>
			<MAIUSCULAS>N</MAIUSCULAS>
			<ASSUMIR/>
			<ASSUMIRINTEIRO/>
			<ASSUMIRREAL/>
			<ASSUMIRLOGICO>S</ASSUMIRLOGICO>
			<ASSUMIRDATA/>
			<MINIMO/>
			<MAXIMO/>
			<CAMPOMESTRE/>
			<CAMPOMESTREORIGINAL/>
			<ANCESTRAL/>
			<PESQUISAR/>
			<RESULTADO/>
			<TEXTO/>
			<FLAGS>0</FLAGS>
			<FLAGS1>8</FLAGS1>
			<FLAGS2>0</FLAGS2>
			<CLIDEF>N</CLIDEF>
			<Z_GRUPO/>
			<OBSERVACOES/>
			<PROPRIEDADE>ContraprestacoesRecRestECanc</PROPRIEDADE>
			<HASH>93FCDA4A1224B5DA451990A6F743D1AF</HASH>
		</CHECK02>
		<CHECK03>
			<TABELA>TV_FORM0073</TABELA>
			<NOME>CHECK03</NOME>
			<LEGENDAFORMULARIO>3 - Eventos conhecidos</LEGENDAFORMULARIO>
			<LEGENDAGRADE>3 - Eventos conhecidos</LEGENDAGRADE>
			<ORDEM>070</ORDEM>
			<DICA>3 - Eventos conhecidos</DICA>
			<PAGINA/>
			<CODIGOINTERNO/>
			<SISTEMA>N</SISTEMA>
			<OPCIONAL>N</OPCIONAL>
			<INVISIVEL>N</INVISIVEL>
			<SOLEITURA>S</SOLEITURA>
			<NOVALINHA>S</NOVALINHA>
			<MOSTRARGRID>S</MOSTRARGRID>
			<ALCLIENTE>N</ALCLIENTE>
			<CLASSE>4</CLASSE>
			<HERDARPERMISSAO/>
			<LARGURA/>
			<MASCARA/>
			<DECIMAIS/>
			<LARGURAFORMULARIO/>
			<MAIUSCULAS>N</MAIUSCULAS>
			<ASSUMIR/>
			<ASSUMIRINTEIRO/>
			<ASSUMIRREAL/>
			<ASSUMIRLOGICO>S</ASSUMIRLOGICO>
			<ASSUMIRDATA/>
			<MINIMO/>
			<MAXIMO/>
			<CAMPOMESTRE/>
			<CAMPOMESTREORIGINAL/>
			<ANCESTRAL/>
			<PESQUISAR/>
			<RESULTADO/>
			<TEXTO/>
			<FLAGS>0</FLAGS>
			<FLAGS1>8</FLAGS1>
			<FLAGS2>0</FLAGS2>
			<CLIDEF>N</CLIDEF>
			<Z_GRUPO/>
			<OBSERVACOES/>
			<PROPRIEDADE>EventosConhecidos</PROPRIEDADE>
			<HASH>E8C834AE6434194B63B4A98EFF8AAD0B</HASH>
		</CHECK03>
		<CHECK04>
			<TABELA>TV_FORM0073</TABELA>
			<NOME>CHECK04</NOME>
			<LEGENDAFORMULARIO>4 - Eventos pagos</LEGENDAFORMULARIO>
			<LEGENDAGRADE>4 - Eventos pagos</LEGENDAGRADE>
			<ORDEM>080</ORDEM>
			<DICA>4 - Eventos pagos</DICA>
			<PAGINA/>
			<CODIGOINTERNO/>
			<SISTEMA>N</SISTEMA>
			<OPCIONAL>N</OPCIONAL>
			<INVISIVEL>N</INVISIVEL>
			<SOLEITURA>S</SOLEITURA>
			<NOVALINHA>S</NOVALINHA>
			<MOSTRARGRID>S</MOSTRARGRID>
			<ALCLIENTE>N</ALCLIENTE>
			<CLASSE>4</CLASSE>
			<HERDARPERMISSAO/>
			<LARGURA/>
			<MASCARA/>
			<DECIMAIS/>
			<LARGURAFORMULARIO/>
			<MAIUSCULAS>N</MAIUSCULAS>
			<ASSUMIR/>
			<ASSUMIRINTEIRO/>
			<ASSUMIRREAL/>
			<ASSUMIRLOGICO>S</ASSUMIRLOGICO>
			<ASSUMIRDATA/>
			<MINIMO/>
			<MAXIMO/>
			<CAMPOMESTRE/>
			<CAMPOMESTREORIGINAL/>
			<ANCESTRAL/>
			<PESQUISAR/>
			<RESULTADO/>
			<TEXTO/>
			<FLAGS>0</FLAGS>
			<FLAGS1>8</FLAGS1>
			<FLAGS2>0</FLAGS2>
			<CLIDEF>N</CLIDEF>
			<Z_GRUPO/>
			<OBSERVACOES/>
			<PROPRIEDADE>EventosPagos</PROPRIEDADE>
			<HASH>9580E54765C37ACDC6DC244F44B0F15C</HASH>
		</CHECK04>
		<CHECK05>
			<TABELA>TV_FORM0073</TABELA>
			<NOME>CHECK05</NOME>
			<LEGENDAFORMULARIO>5 - Comissões emitidas</LEGENDAFORMULARIO>
			<LEGENDAGRADE>5 - Comissões emitidas</LEGENDAGRADE>
			<ORDEM>090</ORDEM>
			<DICA>5 - Comissões emitidas</DICA>
			<PAGINA/>
			<CODIGOINTERNO/>
			<SISTEMA>N</SISTEMA>
			<OPCIONAL>N</OPCIONAL>
			<INVISIVEL>N</INVISIVEL>
			<SOLEITURA>S</SOLEITURA>
			<NOVALINHA>S</NOVALINHA>
			<MOSTRARGRID>S</MOSTRARGRID>
			<ALCLIENTE>N</ALCLIENTE>
			<CLASSE>4</CLASSE>
			<HERDARPERMISSAO/>
			<LARGURA/>
			<MASCARA/>
			<DECIMAIS/>
			<LARGURAFORMULARIO/>
			<MAIUSCULAS>N</MAIUSCULAS>
			<ASSUMIR/>
			<ASSUMIRINTEIRO/>
			<ASSUMIRREAL/>
			<ASSUMIRLOGICO>S</ASSUMIRLOGICO>
			<ASSUMIRDATA/>
			<MINIMO/>
			<MAXIMO/>
			<CAMPOMESTRE/>
			<CAMPOMESTREORIGINAL/>
			<ANCESTRAL/>
			<PESQUISAR/>
			<RESULTADO/>
			<TEXTO/>
			<FLAGS>0</FLAGS>
			<FLAGS1>8</FLAGS1>
			<FLAGS2>0</FLAGS2>
			<CLIDEF>N</CLIDEF>
			<Z_GRUPO/>
			<OBSERVACOES/>
			<PROPRIEDADE>ComissoesEmitidas</PROPRIEDADE>
			<HASH>FA9F7FBC04666E9B8A977E41CD55E6AB</HASH>
		</CHECK05>
		<CHECK06>
			<TABELA>TV_FORM0073</TABELA>
			<NOME>CHECK06</NOME>
			<LEGENDAFORMULARIO>6 - Eventos ressarcidos e recuperados</LEGENDAFORMULARIO>
			<LEGENDAGRADE>6 - Eventos ressarcidos e recuperados</LEGENDAGRADE>
			<ORDEM>100</ORDEM>
			<DICA>6 - Eventos ressarcidos e recuperados</DICA>
			<PAGINA/>
			<CODIGOINTERNO/>
			<SISTEMA>N</SISTEMA>
			<OPCIONAL>N</OPCIONAL>
			<INVISIVEL>N</INVISIVEL>
			<SOLEITURA>S</SOLEITURA>
			<NOVALINHA>S</NOVALINHA>
			<MOSTRARGRID>S</MOSTRARGRID>
			<ALCLIENTE>N</ALCLIENTE>
			<CLASSE>4</CLASSE>
			<HERDARPERMISSAO/>
			<LARGURA/>
			<MASCARA/>
			<DECIMAIS/>
			<LARGURAFORMULARIO/>
			<MAIUSCULAS>N</MAIUSCULAS>
			<ASSUMIR/>
			<ASSUMIRINTEIRO/>
			<ASSUMIRREAL/>
			<ASSUMIRLOGICO>S</ASSUMIRLOGICO>
			<ASSUMIRDATA/>
			<MINIMO/>
			<MAXIMO/>
			<CAMPOMESTRE/>
			<CAMPOMESTREORIGINAL/>
			<ANCESTRAL/>
			<PESQUISAR/>
			<RESULTADO/>
			<TEXTO/>
			<FLAGS>0</FLAGS>
			<FLAGS1>8</FLAGS1>
			<FLAGS2>0</FLAGS2>
			<CLIDEF>N</CLIDEF>
			<Z_GRUPO/>
			<OBSERVACOES/>
			<PROPRIEDADE>EventosRessarcidosERecuperados</PROPRIEDADE>
			<HASH>125EE3B4AA887F4F632C99216D010BC6</HASH>
		</CHECK06>
		<GRPLIVROS>
			<TABELA>TV_FORM0073</TABELA>
			<NOME>GRPLIVROS</NOME>
			<LEGENDAFORMULARIO>Livros</LEGENDAFORMULARIO>
			<LEGENDAGRADE>Livros</LEGENDAGRADE>
			<ORDEM>040</ORDEM>
			<DICA>Livros</DICA>
			<PAGINA/>
			<CODIGOINTERNO/>
			<SISTEMA>N</SISTEMA>
			<OPCIONAL>N</OPCIONAL>
			<INVISIVEL>N</INVISIVEL>
			<SOLEITURA>N</SOLEITURA>
			<NOVALINHA>N</NOVALINHA>
			<MOSTRARGRID>S</MOSTRARGRID>
			<ALCLIENTE>N</ALCLIENTE>
			<CLASSE>15</CLASSE>
			<HERDARPERMISSAO/>
			<LARGURA/>
			<MASCARA/>
			<DECIMAIS/>
			<LARGURAFORMULARIO/>
			<MAIUSCULAS>N</MAIUSCULAS>
			<ASSUMIR/>
			<ASSUMIRINTEIRO/>
			<ASSUMIRREAL/>
			<ASSUMIRLOGICO/>
			<ASSUMIRDATA/>
			<MINIMO/>
			<MAXIMO/>
			<CAMPOMESTRE/>
			<CAMPOMESTREORIGINAL/>
			<ANCESTRAL/>
			<PESQUISAR/>
			<RESULTADO/>
			<TEXTO>1#CHECK01|S|CHECK02|S|CHECK03|S|CHECK04|S|CHECK05|S|CHECK06|S|</TEXTO>
			<FLAGS>0</FLAGS>
			<FLAGS1>8</FLAGS1>
			<FLAGS2>0</FLAGS2>
			<CLIDEF>N</CLIDEF>
			<Z_GRUPO/>
			<OBSERVACOES/>
			<PROPRIEDADE>Livros</PROPRIEDADE>
			<HASH>54EFD9BF73DA2EE70ABC6177CBED7100</HASH>
		</GRPLIVROS>
	</Campos>
</Tabela>
