<?xml version="1.0"?>
<Arvore>
	<Configuracoes>
		<HASH>6B2075717D61994D762A534176C3C7FD</HASH>
		<NOME>2.13 Carga da Rotina Cancelamento</NOME>
		<TIPO>V</TIPO>
		<ORDEM>001</ORDEM>
		<LEGENDA>Cancelamento</LEGENDA>
		<SISTEMA>N</SISTEMA>
		<CLIDEF>N</CLIDEF>
		<FLAGS>0</FLAGS>
		<EXTENSAO/>
		<ORDENAR>N</ORDENAR>
		<TOPICOAJUDA/>
		<TABELA/>
		<GENERICO>N</GENERICO>
		<HASHMACRO/>
	</Configuracoes>
	<Tabelas>
		<ROTINAS_ABERTAS>
			<HASH>5DEF2DF017418BF5D0B6458241E022BC</HASH>
			<VISAO/>
			<CAMPOLIGACAO/>
			<NOME>ROTINAS_ABERTAS</NOME>
			<ORDEM>000</ORDEM>
			<TABELAASSOCIATIVA/>
			<EXTENSAO/>
			<TABELA>SAM_ROTINACANCELAMENTO</TABELA>
			<TEXTO1>CODIGO</TEXTO1>
			<TEXTO2>DESCRICAO</TEXTO2>
			<CARREGAR/>
			<LEGENDA>Rotinas Abertas</LEGENDA>
			<SQLESPECIAL>SITUACAO &lt;&gt; '5'</SQLESPECIAL>
			<SOCOMANDOS>N</SOCOMANDOS>
			<FORMCLASS/>
			<PERMISSAO/>
			<IGNORARPAGINAS>N</IGNORARPAGINAS>
			<UMREGISTRO>N</UMREGISTRO>
			<LER>S</LER>
			<ALTERAR>S</ALTERAR>
			<INCLUIR>S</INCLUIR>
			<EXCLUIR>S</EXCLUIR>
			<CLIDEF>N</CLIDEF>
			<FLAGS>0</FLAGS>
			<CODIGOINTERNO/>
		</ROTINAS_ABERTAS>
		<ROTINAS_GERADAS>
			<HASH>FA54A2D91F7EE640B43B136519D4481E</HASH>
			<VISAO/>
			<CAMPOLIGACAO/>
			<NOME>ROTINAS_GERADAS</NOME>
			<ORDEM>001</ORDEM>
			<TABELAASSOCIATIVA/>
			<EXTENSAO/>
			<TABELA>SAM_ROTINACANCELAMENTO</TABELA>
			<TEXTO1>CODIGO</TEXTO1>
			<TEXTO2>DESCRICAO</TEXTO2>
			<CARREGAR>2.13.1 Processos do Cancelamento</CARREGAR>
			<LEGENDA>Rotinas Geradas</LEGENDA>
			<SQLESPECIAL>SITUACAO = '5' AND SITUACAOPROCESSAR = '1'</SQLESPECIAL>
			<SOCOMANDOS>N</SOCOMANDOS>
			<FORMCLASS/>
			<PERMISSAO/>
			<IGNORARPAGINAS>N</IGNORARPAGINAS>
			<UMREGISTRO>N</UMREGISTRO>
			<LER>S</LER>
			<ALTERAR>N</ALTERAR>
			<INCLUIR>N</INCLUIR>
			<EXCLUIR>S</EXCLUIR>
			<CLIDEF>N</CLIDEF>
			<FLAGS>0</FLAGS>
			<CODIGOINTERNO/>
		</ROTINAS_GERADAS>
		<ROTINAS_PROCESSADAS>
			<HASH>95A94ADAB5C9833CA8F6B5441B85E53F</HASH>
			<VISAO/>
			<CAMPOLIGACAO/>
			<NOME>ROTINAS_PROCESSADAS</NOME>
			<ORDEM>002</ORDEM>
			<TABELAASSOCIATIVA/>
			<EXTENSAO/>
			<TABELA>SAM_ROTINACANCELAMENTO</TABELA>
			<TEXTO1>CODIGO</TEXTO1>
			<TEXTO2>DESCRICAO</TEXTO2>
			<CARREGAR>2.13.1 Processos do Cancelamento</CARREGAR>
			<LEGENDA>Rotinas Processadas</LEGENDA>
			<SQLESPECIAL>SITUACAOPROCESSAR = '5'</SQLESPECIAL>
			<SOCOMANDOS>N</SOCOMANDOS>
			<FORMCLASS/>
			<PERMISSAO/>
			<IGNORARPAGINAS>N</IGNORARPAGINAS>
			<UMREGISTRO>N</UMREGISTRO>
			<LER>S</LER>
			<ALTERAR>N</ALTERAR>
			<INCLUIR>N</INCLUIR>
			<EXCLUIR>N</EXCLUIR>
			<CLIDEF>N</CLIDEF>
			<FLAGS>0</FLAGS>
			<CODIGOINTERNO/>
		</ROTINAS_PROCESSADAS>
	</Tabelas>
</Arvore>
