<?xml version="1.0"?>
<Arvore>
	<Configuracoes>
		<HASH>79285EFDAC09AD7DA8ED6845688179B1</HASH>
		<NOME>6.1.1.1.1.1.1.1.1.-CARGAEVENTOFATURA</NOME>
		<TIPO>V</TIPO>
		<ORDEM>000</ORDEM>
		<LEGENDA>Fatura</LEGENDA>
		<SISTEMA>N</SISTEMA>
		<CLIDEF>N</CLIDEF>
		<FLAGS>0</FLAGS>
		<EXTENSAO/>
		<ORDENAR>N</ORDENAR>
		<TOPICOAJUDA/>
		<TABELA/>
		<GENERICO>N</GENERICO>
		<HASHMACRO/>
	</Configuracoes>
	<Tabelas>
		<GUIAEVENTOFATURA>
			<HASH>258131D222CC6453CEA1AC6EFF6C05BE</HASH>
			<VISAO/>
			<CAMPOLIGACAO/>
			<NOME>GUIAEVENTOFATURA</NOME>
			<ORDEM>050</ORDEM>
			<TABELAASSOCIATIVA>SAM_GUIA_EVENTOS_FATPROVISAO</TABELAASSOCIATIVA>
			<EXTENSAO/>
			<TABELA>SFN_FATURA</TABELA>
			<TEXTO1>NUMERO</TEXTO1>
			<TEXTO2>DATAEMISSAO</TEXTO2>
			<CARREGAR/>
			<LEGENDA>Fatura</LEGENDA>
			<SQLESPECIAL>A.HANDLE = (SELECT X.FATURAPROVISAO FROM SAM_GUIA_EVENTOS_FATPROVISAO X WHERE X.HANDLE=@TABELA|SAM_GUIA_EVENTOS_FATPROVISAO)</SQLESPECIAL>
			<SOCOMANDOS>N</SOCOMANDOS>
			<FORMCLASS/>
			<PERMISSAO/>
			<IGNORARPAGINAS>N</IGNORARPAGINAS>
			<UMREGISTRO>S</UMREGISTRO>
			<LER>S</LER>
			<ALTERAR>N</ALTERAR>
			<INCLUIR>N</INCLUIR>
			<EXCLUIR>N</EXCLUIR>
			<CLIDEF>N</CLIDEF>
			<FLAGS>0</FLAGS>
			<CODIGOINTERNO/>
		</GUIAEVENTOFATURA>
	</Tabelas>
</Arvore>
